
<Mkt>

<Pnt Name="USD-BIIB.O">
  <Undly ID="EUR-IFXGN.DE" PxStrctTyp="EQ_CORRELATION" IssuDtTm="2018-01-29" LastUpdateTm="2018-01-24"/>
  <Msr Val="0.475486077931514" ValTyp="Other" MktDataTyp="ASK"/>
</Pnt>


<Pnt Name="USD-ABT.N">
  <Undly ID="EUR-IFXGN.DE" PxStrctTyp="EQ_CORRELATION" IssuDtTm="2018-01-29" LastUpdateTm="2018-01-24"/>
  <Msr Val="0.515179727789925" ValTyp="Other" MktDataTyp="ASK"/>
</Pnt>


<Pnt Name="CHF-ADEN.S">
  <Undly ID="EUR-IFXGN.DE" PxStrctTyp="EQ_CORRELATION" IssuDtTm="2018-01-29" LastUpdateTm="2018-01-24"/>
  <Msr Val="0.574177068334016" ValTyp="Other" MktDataTyp="ASK"/>
</Pnt>


<Pnt Name="USD-UTX.N">
  <Undly ID="EUR-IFXGN.DE" PxStrctTyp="EQ_CORRELATION" IssuDtTm="2018-01-29" LastUpdateTm="2018-01-17"/>
  <Msr Val="0.516687382655606" ValTyp="Other" MktDataTyp="ASK"/>
</Pnt>


<Pnt Name="USD-KO.N">
  <Undly ID="EUR-IFXGN.DE" PxStrctTyp="EQ_CORRELATION" IssuDtTm="2018-01-29" LastUpdateTm="2018-01-24"/>
  <Msr Val="0.404379186531417" ValTyp="Other" MktDataTyp="ASK"/>
</Pnt>


<Pnt Name="USD-CL.N">
  <Undly ID="EUR-IFXGN.DE" PxStrctTyp="EQ_CORRELATION" IssuDtTm="2018-01-29" LastUpdateTm="2018-01-24"/>
  <Msr Val="0.443577511381733" ValTyp="Other" MktDataTyp="ASK"/>
</Pnt>


<Pnt Name="USD-PXD.N">
  <Undly ID="EUR-IFXGN.DE" PxStrctTyp="EQ_CORRELATION" IssuDtTm="2018-01-29" LastUpdateTm="2018-01-24"/>
  <Msr Val="0.395585762874084" ValTyp="Other" MktDataTyp="ASK"/>
</Pnt>


<Pnt Name="EUR-REP.MC">
  <Undly ID="EUR-IFXGN.DE" PxStrctTyp="EQ_CORRELATION" IssuDtTm="2018-01-29" LastUpdateTm="2018-01-24"/>
  <Msr Val="0.509563154387187" ValTyp="Other" MktDataTyp="ASK"/>
</Pnt>


<Pnt Name="USD-AAL.OQ">
  <Undly ID="EUR-IFXGN.DE" PxStrctTyp="EQ_CORRELATION" IssuDtTm="2018-01-29" LastUpdateTm="2018-01-24"/>
  <Msr Val="0.529167410579807" ValTyp="Other" MktDataTyp="ASK"/>
</Pnt>


<Pnt Name="JPY-NIKKEI 225">
  <Undly ID="EUR-IFXGN.DE" PxStrctTyp="EQ_CORRELATION" IssuDtTm="2018-01-29" LastUpdateTm="2018-01-24"/>
  <Msr Val="0.594342464337443" ValTyp="Other" MktDataTyp="ASK"/>
</Pnt>


<Pnt Name="EUR-FTE.PA">
  <Undly ID="EUR-IFXGN.DE" PxStrctTyp="EQ_CORRELATION" IssuDtTm="2018-01-29" LastUpdateTm="2018-01-24"/>
  <Msr Val="0.544139607663495" ValTyp="Other" MktDataTyp="ASK"/>
</Pnt>


<Pnt Name="USD-PRU.N">
  <Undly ID="EUR-IFXGN.DE" PxStrctTyp="EQ_CORRELATION" IssuDtTm="2018-01-29" LastUpdateTm="2018-01-24"/>
  <Msr Val="0.560355675952289" ValTyp="Other" MktDataTyp="ASK"/>
</Pnt>


<Pnt Name="USD-CVX.N">
  <Undly ID="EUR-IFXGN.DE" PxStrctTyp="EQ_CORRELATION" IssuDtTm="2018-01-29" LastUpdateTm="2018-01-24"/>
  <Msr Val="0.456838634332519" ValTyp="Other" MktDataTyp="ASK"/>
</Pnt>


<Pnt Name="USD-M.N">
  <Undly ID="EUR-IFXGN.DE" PxStrctTyp="EQ_CORRELATION" IssuDtTm="2018-01-29" LastUpdateTm="2018-01-24"/>
  <Msr Val="0.44819089334145" ValTyp="Other" MktDataTyp="ASK"/>
</Pnt>


<Pnt Name="USD-PFE.N">
  <Undly ID="EUR-IFXGN.DE" PxStrctTyp="EQ_CORRELATION" IssuDtTm="2018-01-29" LastUpdateTm="2018-01-24"/>
  <Msr Val="0.469754331897987" ValTyp="Other" MktDataTyp="ASK"/>
</Pnt>


<Pnt Name="GBP-AAL.L">
  <Undly ID="EUR-IFXGN.DE" PxStrctTyp="EQ_CORRELATION" IssuDtTm="2018-01-29" LastUpdateTm="2018-01-24"/>
  <Msr Val="0.427200498132091" ValTyp="Other" MktDataTyp="ASK"/>
</Pnt>


<Pnt Name="EUR-CBKG.DE">
  <Undly ID="EUR-IFXGN.DE" PxStrctTyp="EQ_CORRELATION" IssuDtTm="2018-01-29" LastUpdateTm="2018-01-24"/>
  <Msr Val="0.557907059043964" ValTyp="Other" MktDataTyp="ASK"/>
</Pnt>


<Pnt Name="EUR-SAPG.DE">
  <Undly ID="EUR-IFXGN.DE" PxStrctTyp="EQ_CORRELATION" IssuDtTm="2018-01-29" LastUpdateTm="2018-01-24"/>
  <Msr Val="0.684947787996924" ValTyp="Other" MktDataTyp="ASK"/>
</Pnt>


<Pnt Name="USD-WFC.N">
  <Undly ID="EUR-IFXGN.DE" PxStrctTyp="EQ_CORRELATION" IssuDtTm="2018-01-29" LastUpdateTm="2018-01-17"/>
  <Msr Val="0.518149424487309" ValTyp="Other" MktDataTyp="ASK"/>
</Pnt>


<Pnt Name="USD-CX.N">
  <Undly ID="EUR-IFXGN.DE" PxStrctTyp="EQ_CORRELATION" IssuDtTm="2018-01-29" LastUpdateTm="2018-01-24"/>
  <Msr Val="0.497866828876889" ValTyp="Other" MktDataTyp="ASK"/>
</Pnt>


<Pnt Name="USD-CAT.N">
  <Undly ID="EUR-IFXGN.DE" PxStrctTyp="EQ_CORRELATION" IssuDtTm="2018-01-29" LastUpdateTm="2018-01-24"/>
  <Msr Val="0.492959175714748" ValTyp="Other" MktDataTyp="ASK"/>
</Pnt>


<Pnt Name="USD-SO.N">
  <Undly ID="EUR-IFXGN.DE" PxStrctTyp="EQ_CORRELATION" IssuDtTm="2018-01-29" LastUpdateTm="2018-01-17"/>
  <Msr Val="0.311392989265" ValTyp="Other" MktDataTyp="ASK"/>
</Pnt>


<Pnt Name="EUR-PHG.AS">
  <Undly ID="EUR-IFXGN.DE" PxStrctTyp="EQ_CORRELATION" IssuDtTm="2018-01-29" LastUpdateTm="2018-01-24"/>
  <Msr Val="0.594230636186165" ValTyp="Other" MktDataTyp="ASK"/>
</Pnt>


<Pnt Name="EUR-ISPA.AS">
  <Undly ID="EUR-IFXGN.DE" PxStrctTyp="EQ_CORRELATION" IssuDtTm="2018-01-29" LastUpdateTm="2018-01-24"/>
  <Msr Val="0.498474930711729" ValTyp="Other" MktDataTyp="ASK"/>
</Pnt>


<Pnt Name="USD-TWTR.N">
  <Undly ID="EUR-IFXGN.DE" PxStrctTyp="EQ_CORRELATION" IssuDtTm="2018-01-29" LastUpdateTm="2018-01-17"/>
  <Msr Val="0.452832853959294" ValTyp="Other" MktDataTyp="ASK"/>
</Pnt>


<Pnt Name="SEK-OMX INDEX">
  <Undly ID="EUR-IFXGN.DE" PxStrctTyp="EQ_CORRELATION" IssuDtTm="2018-01-29" LastUpdateTm="2018-01-24"/>
  <Msr Val="0.685918667791083" ValTyp="Other" MktDataTyp="ASK"/>
</Pnt>


<Pnt Name="GBP-GSK.L">
  <Undly ID="EUR-IFXGN.DE" PxStrctTyp="EQ_CORRELATION" IssuDtTm="2018-01-29" LastUpdateTm="2018-01-24"/>
  <Msr Val="0.452750137335732" ValTyp="Other" MktDataTyp="ASK"/>
</Pnt>


<Pnt Name="USD-XLF.N">
  <Undly ID="EUR-IFXGN.DE" PxStrctTyp="EQ_CORRELATION" IssuDtTm="2018-01-29" LastUpdateTm="2018-01-17"/>
  <Msr Val="0.584931809076369" ValTyp="Other" MktDataTyp="ASK"/>
</Pnt>


<Pnt Name="EUROSTOXX BANK">
  <Undly ID="EUR-IFXGN.DE" PxStrctTyp="EQ_CORRELATION" IssuDtTm="2018-01-29" LastUpdateTm="2018-01-24"/>
  <Msr Val="0.611205652480279" ValTyp="Other" MktDataTyp="ASK"/>
</Pnt>


<Pnt Name="USD-XLB.N">
  <Undly ID="EUR-IFXGN.DE" PxStrctTyp="EQ_CORRELATION" IssuDtTm="2018-01-29" LastUpdateTm="2018-01-17"/>
  <Msr Val="0.547243763039626" ValTyp="Other" MktDataTyp="ASK"/>
</Pnt>


<Pnt Name="USD-EWJ.N">
  <Undly ID="EUR-IFXGN.DE" PxStrctTyp="EQ_CORRELATION" IssuDtTm="2018-01-29" LastUpdateTm="2018-01-24"/>
  <Msr Val="0.557590493445091" ValTyp="Other" MktDataTyp="ASK"/>
</Pnt>


<Pnt Name="CHF-SLHN.S">
  <Undly ID="EUR-IFXGN.DE" PxStrctTyp="EQ_CORRELATION" IssuDtTm="2018-01-29" LastUpdateTm="2018-01-24"/>
  <Msr Val="0.579924521467575" ValTyp="Other" MktDataTyp="ASK"/>
</Pnt>


<Pnt Name="USD-MWD.N">
  <Undly ID="EUR-IFXGN.DE" PxStrctTyp="EQ_CORRELATION" IssuDtTm="2018-01-29" LastUpdateTm="2018-01-24"/>
  <Msr Val="0.560616798786594" ValTyp="Other" MktDataTyp="ASK"/>
</Pnt>


<Pnt Name="USD-MA.N">
  <Undly ID="EUR-IFXGN.DE" PxStrctTyp="EQ_CORRELATION" IssuDtTm="2018-01-29" LastUpdateTm="2018-01-24"/>
  <Msr Val="0.523383640354231" ValTyp="Other" MktDataTyp="ASK"/>
</Pnt>


<Pnt Name="USD-GILD.O">
  <Undly ID="EUR-IFXGN.DE" PxStrctTyp="EQ_CORRELATION" IssuDtTm="2018-01-29" LastUpdateTm="2018-01-24"/>
  <Msr Val="0.459013233022955" ValTyp="Other" MktDataTyp="ASK"/>
</Pnt>


<Pnt Name="CHF-UHR.S">
  <Undly ID="EUR-IFXGN.DE" PxStrctTyp="EQ_CORRELATION" IssuDtTm="2018-01-29" LastUpdateTm="2018-01-24"/>
  <Msr Val="0.492414228382362" ValTyp="Other" MktDataTyp="ASK"/>
</Pnt>


<Pnt Name="USD-K.N">
  <Undly ID="EUR-IFXGN.DE" PxStrctTyp="EQ_CORRELATION" IssuDtTm="2018-01-29" LastUpdateTm="2018-01-24"/>
  <Msr Val="0.408048917717292" ValTyp="Other" MktDataTyp="ASK"/>
</Pnt>


<Pnt Name="USD-BLK.N">
  <Undly ID="EUR-IFXGN.DE" PxStrctTyp="EQ_CORRELATION" IssuDtTm="2018-01-29" LastUpdateTm="2018-01-24"/>
  <Msr Val="0.566078650818064" ValTyp="Other" MktDataTyp="ASK"/>
</Pnt>


<Pnt Name="USD-EWW.N">
  <Undly ID="EUR-IFXGN.DE" PxStrctTyp="EQ_CORRELATION" IssuDtTm="2018-01-29" LastUpdateTm="2018-01-24"/>
  <Msr Val="0.51993965956597" ValTyp="Other" MktDataTyp="ASK"/>
</Pnt>


<Pnt Name="USD-YHOO.O">
  <Undly ID="EUR-IFXGN.DE" PxStrctTyp="EQ_CORRELATION" IssuDtTm="2018-01-29" LastUpdateTm="2017-10-16"/>
  <Msr Val="0.513767925793684" ValTyp="Other" MktDataTyp="ASK"/>
</Pnt>


<Pnt Name="USD-CRM.N">
  <Undly ID="EUR-IFXGN.DE" PxStrctTyp="EQ_CORRELATION" IssuDtTm="2018-01-29" LastUpdateTm="2018-01-24"/>
  <Msr Val="0.51956256716345" ValTyp="Other" MktDataTyp="ASK"/>
</Pnt>


<Pnt Name="USD-EEM.N">
  <Undly ID="EUR-IFXGN.DE" PxStrctTyp="EQ_CORRELATION" IssuDtTm="2018-01-29" LastUpdateTm="2018-01-24"/>
  <Msr Val="0.572572473469351" ValTyp="Other" MktDataTyp="ASK"/>
</Pnt>


<Pnt Name="USD-HESS.N">
  <Undly ID="EUR-IFXGN.DE" PxStrctTyp="EQ_CORRELATION" IssuDtTm="2018-01-29" LastUpdateTm="2018-01-24"/>
  <Msr Val="0.423581053100268" ValTyp="Other" MktDataTyp="ASK"/>
</Pnt>


<Pnt Name="USD-AXP.N">
  <Undly ID="EUR-IFXGN.DE" PxStrctTyp="EQ_CORRELATION" IssuDtTm="2018-01-29" LastUpdateTm="2018-01-24"/>
  <Msr Val="0.488587432690253" ValTyp="Other" MktDataTyp="ASK"/>
</Pnt>


<Pnt Name="EUR-HEIN.AS">
  <Undly ID="EUR-IFXGN.DE" PxStrctTyp="EQ_CORRELATION" IssuDtTm="2018-01-29" LastUpdateTm="2018-01-24"/>
  <Msr Val="0.526842420404765" ValTyp="Other" MktDataTyp="ASK"/>
</Pnt>


<Pnt Name="USD-ADP.O">
  <Undly ID="EUR-IFXGN.DE" PxStrctTyp="EQ_CORRELATION" IssuDtTm="2018-01-29" LastUpdateTm="2018-01-24"/>
  <Msr Val="0.500264112586787" ValTyp="Other" MktDataTyp="ASK"/>
</Pnt>


<Pnt Name="USD-MO.N">
  <Undly ID="EUR-IFXGN.DE" PxStrctTyp="EQ_CORRELATION" IssuDtTm="2018-01-29" LastUpdateTm="2018-01-24"/>
  <Msr Val="0.413956529829683" ValTyp="Other" MktDataTyp="ASK"/>
</Pnt>


<Pnt Name="USD-CMCSA.O">
  <Undly ID="EUR-IFXGN.DE" PxStrctTyp="EQ_CORRELATION" IssuDtTm="2018-01-29" LastUpdateTm="2018-01-24"/>
  <Msr Val="0.468147533635793" ValTyp="Other" MktDataTyp="ASK"/>
</Pnt>


<Pnt Name="USD-POT.N">
  <Undly ID="EUR-IFXGN.DE" PxStrctTyp="EQ_CORRELATION" IssuDtTm="2018-01-29" LastUpdateTm="2018-01-24"/>
  <Msr Val="0.445547343396935" ValTyp="Other" MktDataTyp="ASK"/>
</Pnt>


<Pnt Name="USD-MSFT.O">
  <Undly ID="EUR-IFXGN.DE" PxStrctTyp="EQ_CORRELATION" IssuDtTm="2018-01-29" LastUpdateTm="2018-01-24"/>
  <Msr Val="0.525125338059771" ValTyp="Other" MktDataTyp="ASK"/>
</Pnt>


<Pnt Name="USD-LMT.N">
  <Undly ID="EUR-IFXGN.DE" PxStrctTyp="EQ_CORRELATION" IssuDtTm="2018-01-29" LastUpdateTm="2018-01-24"/>
  <Msr Val="0.460803776073443" ValTyp="Other" MktDataTyp="ASK"/>
</Pnt>


<Pnt Name="USD-BMY.N">
  <Undly ID="EUR-IFXGN.DE" PxStrctTyp="EQ_CORRELATION" IssuDtTm="2018-01-29" LastUpdateTm="2018-01-24"/>
  <Msr Val="0.468255342965698" ValTyp="Other" MktDataTyp="ASK"/>
</Pnt>


<Pnt Name="USD-SPX 500 IND">
  <Undly ID="EUR-IFXGN.DE" PxStrctTyp="EQ_CORRELATION" IssuDtTm="2018-01-29" LastUpdateTm="2018-01-17"/>
  <Msr Val="0.627690687259316" ValTyp="Other" MktDataTyp="ASK"/>
</Pnt>


<Pnt Name="IPC">
  <Undly ID="EUR-IFXGN.DE" PxStrctTyp="EQ_CORRELATION" IssuDtTm="2018-01-29" LastUpdateTm="2018-01-24"/>
  <Msr Val="0.525335138768225" ValTyp="Other" MktDataTyp="ASK"/>
</Pnt>


<Pnt Name="USD-WDC.P">
  <Undly ID="EUR-IFXGN.DE" PxStrctTyp="EQ_CORRELATION" IssuDtTm="2018-01-29" LastUpdateTm="2018-01-17"/>
  <Msr Val="0.539241528396167" ValTyp="Other" MktDataTyp="ASK"/>
</Pnt>


<Pnt Name="USD-MAR.N">
  <Undly ID="EUR-IFXGN.DE" PxStrctTyp="EQ_CORRELATION" IssuDtTm="2018-01-29" LastUpdateTm="2018-01-24"/>
  <Msr Val="0.512896336391121" ValTyp="Other" MktDataTyp="ASK"/>
</Pnt>


<Pnt Name="CHF-ROCZG.S">
  <Undly ID="EUR-IFXGN.DE" PxStrctTyp="EQ_CORRELATION" IssuDtTm="2018-01-29" LastUpdateTm="2018-01-24"/>
  <Msr Val="0.509953679188814" ValTyp="Other" MktDataTyp="ASK"/>
</Pnt>


<Pnt Name="GBP-BATS.L">
  <Undly ID="EUR-IFXGN.DE" PxStrctTyp="EQ_CORRELATION" IssuDtTm="2018-01-29" LastUpdateTm="2018-01-24"/>
  <Msr Val="0.480645185732117" ValTyp="Other" MktDataTyp="ASK"/>
</Pnt>


<Pnt Name="USD-GOOAV.O">
  <Undly ID="EUR-IFXGN.DE" PxStrctTyp="EQ_CORRELATION" IssuDtTm="2018-01-29" LastUpdateTm="2018-01-24"/>
  <Msr Val="0.531469999519296" ValTyp="Other" MktDataTyp="ASK"/>
</Pnt>


<Pnt Name="EUR-CAC IND">
  <Undly ID="EUR-IFXGN.DE" PxStrctTyp="EQ_CORRELATION" IssuDtTm="2018-01-29" LastUpdateTm="2018-01-24"/>
  <Msr Val="0.674550977287941" ValTyp="Other" MktDataTyp="ASK"/>
</Pnt>


<Pnt Name="USD-XOM.N">
  <Undly ID="EUR-IFXGN.DE" PxStrctTyp="EQ_CORRELATION" IssuDtTm="2018-01-29" LastUpdateTm="2018-01-17"/>
  <Msr Val="0.441194128479434" ValTyp="Other" MktDataTyp="ASK"/>
</Pnt>


<Pnt Name="USD-JNJ.N">
  <Undly ID="EUR-IFXGN.DE" PxStrctTyp="EQ_CORRELATION" IssuDtTm="2018-01-29" LastUpdateTm="2018-01-24"/>
  <Msr Val="0.4653659091927" ValTyp="Other" MktDataTyp="ASK"/>
</Pnt>


<Pnt Name="EUR-RDSA.AS">
  <Undly ID="EUR-IFXGN.DE" PxStrctTyp="EQ_CORRELATION" IssuDtTm="2018-01-29" LastUpdateTm="2018-01-24"/>
  <Msr Val="0.472495222183826" ValTyp="Other" MktDataTyp="ASK"/>
</Pnt>


<Pnt Name="USD-NEM.N">
  <Undly ID="EUR-IFXGN.DE" PxStrctTyp="EQ_CORRELATION" IssuDtTm="2018-01-29" LastUpdateTm="2018-01-24"/>
  <Msr Val="0.311392989265" ValTyp="Other" MktDataTyp="ASK"/>
</Pnt>


<Pnt Name="EUR-SGEF.PA">
  <Undly ID="EUR-IFXGN.DE" PxStrctTyp="EQ_CORRELATION" IssuDtTm="2018-01-29" LastUpdateTm="2018-01-24"/>
  <Msr Val="0.573959910690866" ValTyp="Other" MktDataTyp="ASK"/>
</Pnt>


<Pnt Name="EUR-EONG.DE">
  <Undly ID="EUR-IFXGN.DE" PxStrctTyp="EQ_CORRELATION" IssuDtTm="2018-01-29" LastUpdateTm="2018-01-24"/>
  <Msr Val="0.556016727890685" ValTyp="Other" MktDataTyp="ASK"/>
</Pnt>


<Pnt Name="USD-PCLN.O">
  <Undly ID="EUR-IFXGN.DE" PxStrctTyp="EQ_CORRELATION" IssuDtTm="2018-01-29" LastUpdateTm="2018-01-24"/>
  <Msr Val="0.481536295654715" ValTyp="Other" MktDataTyp="ASK"/>
</Pnt>


<Pnt Name="SEK-NDA.ST">
  <Undly ID="EUR-IFXGN.DE" PxStrctTyp="EQ_CORRELATION" IssuDtTm="2018-01-29" LastUpdateTm="2018-01-24"/>
  <Msr Val="0.619580558666784" ValTyp="Other" MktDataTyp="ASK"/>
</Pnt>


<Pnt Name="USD-ALLY.N">
  <Undly ID="EUR-IFXGN.DE" PxStrctTyp="EQ_CORRELATION" IssuDtTm="2018-01-29" LastUpdateTm="2018-01-24"/>
  <Msr Val="0.478469722268413" ValTyp="Other" MktDataTyp="ASK"/>
</Pnt>


<Pnt Name="USD-BBY.N">
  <Undly ID="EUR-IFXGN.DE" PxStrctTyp="EQ_CORRELATION" IssuDtTm="2018-01-29" LastUpdateTm="2018-01-24"/>
  <Msr Val="0.463546317416775" ValTyp="Other" MktDataTyp="ASK"/>
</Pnt>


<Pnt Name="KOSPI 200 IND">
  <Undly ID="EUR-IFXGN.DE" PxStrctTyp="EQ_CORRELATION" IssuDtTm="2018-01-29" LastUpdateTm="2018-01-24"/>
  <Msr Val="0.517363953391917" ValTyp="Other" MktDataTyp="ASK"/>
</Pnt>


<Pnt Name="EUR-NOK1V.HE">
  <Undly ID="EUR-IFXGN.DE" PxStrctTyp="EQ_CORRELATION" IssuDtTm="2018-01-29" LastUpdateTm="2018-01-24"/>
  <Msr Val="0.570726615269103" ValTyp="Other" MktDataTyp="ASK"/>
</Pnt>


<Pnt Name="EUR-BIN.MI">
  <Undly ID="EUR-IFXGN.DE" PxStrctTyp="EQ_CORRELATION" IssuDtTm="2018-01-29" LastUpdateTm="2018-01-24"/>
  <Msr Val="0.579054964196904" ValTyp="Other" MktDataTyp="ASK"/>
</Pnt>


<Pnt Name="USD-FB.O">
  <Undly ID="EUR-IFXGN.DE" PxStrctTyp="EQ_CORRELATION" IssuDtTm="2018-01-29" LastUpdateTm="2018-01-24"/>
  <Msr Val="0.529565866131959" ValTyp="Other" MktDataTyp="ASK"/>
</Pnt>


<Pnt Name="USD-MCD.N">
  <Undly ID="EUR-IFXGN.DE" PxStrctTyp="EQ_CORRELATION" IssuDtTm="2018-01-29" LastUpdateTm="2018-01-24"/>
  <Msr Val="0.4171289311704" ValTyp="Other" MktDataTyp="ASK"/>
</Pnt>


<Pnt Name="EUR-SCH.MC">
  <Undly ID="EUR-IFXGN.DE" PxStrctTyp="EQ_CORRELATION" IssuDtTm="2018-01-29" LastUpdateTm="2018-01-24"/>
  <Msr Val="0.571388714995294" ValTyp="Other" MktDataTyp="ASK"/>
</Pnt>


<Pnt Name="CHF-ABBN.S">
  <Undly ID="EUR-IFXGN.DE" PxStrctTyp="EQ_CORRELATION" IssuDtTm="2018-01-29" LastUpdateTm="2018-01-24"/>
  <Msr Val="0.591588253122668" ValTyp="Other" MktDataTyp="ASK"/>
</Pnt>


<Pnt Name="USD-TRV.N">
  <Undly ID="EUR-IFXGN.DE" PxStrctTyp="EQ_CORRELATION" IssuDtTm="2018-01-29" LastUpdateTm="2018-01-17"/>
  <Msr Val="0.466725075091231" ValTyp="Other" MktDataTyp="ASK"/>
</Pnt>


<Pnt Name="USD-BAP.N">
  <Undly ID="EUR-IFXGN.DE" PxStrctTyp="EQ_CORRELATION" IssuDtTm="2018-01-29" LastUpdateTm="2018-01-24"/>
  <Msr Val="0.466955486852529" ValTyp="Other" MktDataTyp="ASK"/>
</Pnt>


<Pnt Name="USD-LOW.N">
  <Undly ID="EUR-IFXGN.DE" PxStrctTyp="EQ_CORRELATION" IssuDtTm="2018-01-29" LastUpdateTm="2018-01-24"/>
  <Msr Val="0.497877650893223" ValTyp="Other" MktDataTyp="ASK"/>
</Pnt>


<Pnt Name="EUR-ITX.MC">
  <Undly ID="EUR-IFXGN.DE" PxStrctTyp="EQ_CORRELATION" IssuDtTm="2018-01-29" LastUpdateTm="2018-01-24"/>
  <Msr Val="0.57515245393945" ValTyp="Other" MktDataTyp="ASK"/>
</Pnt>


<Pnt Name="EUR-ENEI.MI">
  <Undly ID="EUR-IFXGN.DE" PxStrctTyp="EQ_CORRELATION" IssuDtTm="2018-01-29" LastUpdateTm="2018-01-24"/>
  <Msr Val="0.560893125922986" ValTyp="Other" MktDataTyp="ASK"/>
</Pnt>


<Pnt Name="EUR-ESSI.PA">
  <Undly ID="EUR-IFXGN.DE" PxStrctTyp="EQ_CORRELATION" IssuDtTm="2018-01-29" LastUpdateTm="2018-01-24"/>
  <Msr Val="0.5829331260958" ValTyp="Other" MktDataTyp="ASK"/>
</Pnt>


<Pnt Name="USD-DHR.N">
  <Undly ID="EUR-IFXGN.DE" PxStrctTyp="EQ_CORRELATION" IssuDtTm="2018-01-29" LastUpdateTm="2018-01-24"/>
  <Msr Val="0.540765550508836" ValTyp="Other" MktDataTyp="ASK"/>
</Pnt>


<Pnt Name="EUR-AXAF.PA">
  <Undly ID="EUR-IFXGN.DE" PxStrctTyp="EQ_CORRELATION" IssuDtTm="2018-01-29" LastUpdateTm="2018-01-24"/>
  <Msr Val="0.61227530806224" ValTyp="Other" MktDataTyp="ASK"/>
</Pnt>


<Pnt Name="USD-JD.O">
  <Undly ID="EUR-IFXGN.DE" PxStrctTyp="EQ_CORRELATION" IssuDtTm="2018-01-29" LastUpdateTm="2018-01-24"/>
  <Msr Val="0.480640453127734" ValTyp="Other" MktDataTyp="ASK"/>
</Pnt>


<Pnt Name="EUR-FIA.MI">
  <Undly ID="EUR-IFXGN.DE" PxStrctTyp="EQ_CORRELATION" IssuDtTm="2018-01-29" LastUpdateTm="2018-01-24"/>
  <Msr Val="0.582824114472313" ValTyp="Other" MktDataTyp="ASK"/>
</Pnt>


<Pnt Name="USD-IBM.N">
  <Undly ID="EUR-IFXGN.DE" PxStrctTyp="EQ_CORRELATION" IssuDtTm="2018-01-29" LastUpdateTm="2018-01-24"/>
  <Msr Val="0.487036901711536" ValTyp="Other" MktDataTyp="ASK"/>
</Pnt>


<Pnt Name="USD-NEE.N">
  <Undly ID="EUR-IFXGN.DE" PxStrctTyp="EQ_CORRELATION" IssuDtTm="2018-01-29" LastUpdateTm="2018-01-24"/>
  <Msr Val="0.345704385368836" ValTyp="Other" MktDataTyp="ASK"/>
</Pnt>


<Pnt Name="EUR-CARR.PA">
  <Undly ID="EUR-IFXGN.DE" PxStrctTyp="EQ_CORRELATION" IssuDtTm="2018-01-29" LastUpdateTm="2018-01-24"/>
  <Msr Val="0.597081748901387" ValTyp="Other" MktDataTyp="ASK"/>
</Pnt>


<Pnt Name="USD-TSLA.O">
  <Undly ID="EUR-IFXGN.DE" PxStrctTyp="EQ_CORRELATION" IssuDtTm="2018-01-29" LastUpdateTm="2018-01-17"/>
  <Msr Val="0.466720673882696" ValTyp="Other" MktDataTyp="ASK"/>
</Pnt>


<Pnt Name="CHF-GIVZN.S">
  <Undly ID="EUR-IFXGN.DE" PxStrctTyp="EQ_CORRELATION" IssuDtTm="2018-01-29" LastUpdateTm="2018-01-24"/>
  <Msr Val="0.533124778994285" ValTyp="Other" MktDataTyp="ASK"/>
</Pnt>


<Pnt Name="EUR-BNPP.PA">
  <Undly ID="EUR-IFXGN.DE" PxStrctTyp="EQ_CORRELATION" IssuDtTm="2018-01-29" LastUpdateTm="2018-01-24"/>
  <Msr Val="0.593856123691666" ValTyp="Other" MktDataTyp="ASK"/>
</Pnt>


<Pnt Name="USD-DUK.N">
  <Undly ID="EUR-IFXGN.DE" PxStrctTyp="EQ_CORRELATION" IssuDtTm="2018-01-29" LastUpdateTm="2018-01-24"/>
  <Msr Val="0.311392989265" ValTyp="Other" MktDataTyp="ASK"/>
</Pnt>


<Pnt Name="USD-HON.N">
  <Undly ID="EUR-IFXGN.DE" PxStrctTyp="EQ_CORRELATION" IssuDtTm="2018-01-29" LastUpdateTm="2018-01-24"/>
  <Msr Val="0.576103023658366" ValTyp="Other" MktDataTyp="ASK"/>
</Pnt>


<Pnt Name="EUR-VIE.PA">
  <Undly ID="EUR-IFXGN.DE" PxStrctTyp="EQ_CORRELATION" IssuDtTm="2018-01-29" LastUpdateTm="2018-01-24"/>
  <Msr Val="0.542284271778268" ValTyp="Other" MktDataTyp="ASK"/>
</Pnt>


<Pnt Name="EUR-DCXGN.DE">
  <Undly ID="EUR-IFXGN.DE" PxStrctTyp="EQ_CORRELATION" IssuDtTm="2018-01-29" LastUpdateTm="2018-01-24"/>
  <Msr Val="0.662243651801527" ValTyp="Other" MktDataTyp="ASK"/>
</Pnt>


<Pnt Name="CHF-CFR.S">
  <Undly ID="EUR-IFXGN.DE" PxStrctTyp="EQ_CORRELATION" IssuDtTm="2018-01-29" LastUpdateTm="2018-01-24"/>
  <Msr Val="0.516159830731123" ValTyp="Other" MktDataTyp="ASK"/>
</Pnt>


<Pnt Name="USD-ADBE.O">
  <Undly ID="EUR-IFXGN.DE" PxStrctTyp="EQ_CORRELATION" IssuDtTm="2018-01-29" LastUpdateTm="2018-01-24"/>
  <Msr Val="0.535091184818623" ValTyp="Other" MktDataTyp="ASK"/>
</Pnt>


<Pnt Name="USD-MDT.N">
  <Undly ID="EUR-IFXGN.DE" PxStrctTyp="EQ_CORRELATION" IssuDtTm="2018-01-29" LastUpdateTm="2018-01-24"/>
  <Msr Val="0.493571969792703" ValTyp="Other" MktDataTyp="ASK"/>
</Pnt>


<Pnt Name="GBP-BP/.L">
  <Undly ID="EUR-IFXGN.DE" PxStrctTyp="EQ_CORRELATION" IssuDtTm="2018-01-29" LastUpdateTm="2018-01-24"/>
  <Msr Val="0.45088093230107" ValTyp="Other" MktDataTyp="ASK"/>
</Pnt>


<Pnt Name="USD-AVGO.O">
  <Undly ID="EUR-IFXGN.DE" PxStrctTyp="EQ_CORRELATION" IssuDtTm="2018-01-29" LastUpdateTm="2018-01-24"/>
  <Msr Val="0.610507661436729" ValTyp="Other" MktDataTyp="ASK"/>
</Pnt>


<Pnt Name="EUR-SOGN.PA">
  <Undly ID="EUR-IFXGN.DE" PxStrctTyp="EQ_CORRELATION" IssuDtTm="2018-01-29" LastUpdateTm="2018-01-24"/>
  <Msr Val="0.592036352158434" ValTyp="Other" MktDataTyp="ASK"/>
</Pnt>


<Pnt Name="USD-C.N">
  <Undly ID="EUR-IFXGN.DE" PxStrctTyp="EQ_CORRELATION" IssuDtTm="2018-01-29" LastUpdateTm="2018-01-24"/>
  <Msr Val="0.525607978637337" ValTyp="Other" MktDataTyp="ASK"/>
</Pnt>


<Pnt Name="EUR-SIEGN.DE">
  <Undly ID="EUR-IFXGN.DE" PxStrctTyp="EQ_CORRELATION" IssuDtTm="2018-01-29" LastUpdateTm="2018-01-24"/>
  <Msr Val="0.641229857542725" ValTyp="Other" MktDataTyp="ASK"/>
</Pnt>


<Pnt Name="EUR-ING.AS">
  <Undly ID="EUR-IFXGN.DE" PxStrctTyp="EQ_CORRELATION" IssuDtTm="2018-01-29" LastUpdateTm="2018-01-24"/>
  <Msr Val="0.619014794922981" ValTyp="Other" MktDataTyp="ASK"/>
</Pnt>


<Pnt Name="EUR-DTEG.DE">
  <Undly ID="EUR-IFXGN.DE" PxStrctTyp="EQ_CORRELATION" IssuDtTm="2018-01-29" LastUpdateTm="2018-01-24"/>
  <Msr Val="0.603692183735944" ValTyp="Other" MktDataTyp="ASK"/>
</Pnt>


<Pnt Name="USD-SBUX.OK">
  <Undly ID="EUR-IFXGN.DE" PxStrctTyp="EQ_CORRELATION" IssuDtTm="2018-01-29" LastUpdateTm="2018-01-24"/>
  <Msr Val="0.480507528861339" ValTyp="Other" MktDataTyp="ASK"/>
</Pnt>


<Pnt Name="GBP-LLOY.L">
  <Undly ID="EUR-IFXGN.DE" PxStrctTyp="EQ_CORRELATION" IssuDtTm="2018-01-29" LastUpdateTm="2018-01-24"/>
  <Msr Val="0.53022504023418" ValTyp="Other" MktDataTyp="ASK"/>
</Pnt>


<Pnt Name="USD-AMZN.O">
  <Undly ID="EUR-IFXGN.DE" PxStrctTyp="EQ_CORRELATION" IssuDtTm="2018-01-29" LastUpdateTm="2018-01-24"/>
  <Msr Val="0.476698722909235" ValTyp="Other" MktDataTyp="ASK"/>
</Pnt>


<Pnt Name="USD-AEP.N">
  <Undly ID="EUR-IFXGN.DE" PxStrctTyp="EQ_CORRELATION" IssuDtTm="2018-01-29" LastUpdateTm="2018-01-24"/>
  <Msr Val="0.3132968358193" ValTyp="Other" MktDataTyp="ASK"/>
</Pnt>


<Pnt Name="USD-FEZ.P">
  <Undly ID="EUR-IFXGN.DE" PxStrctTyp="EQ_CORRELATION" IssuDtTm="2018-01-29" LastUpdateTm="2018-01-24"/>
  <Msr Val="0.652808362420758" ValTyp="Other" MktDataTyp="ASK"/>
</Pnt>


<Pnt Name="EUR-DAX IND">
  <Undly ID="EUR-IFXGN.DE" PxStrctTyp="EQ_CORRELATION" IssuDtTm="2018-01-29" LastUpdateTm="2018-01-24"/>
  <Msr Val="0.72159981192114" ValTyp="Other" MktDataTyp="ASK"/>
</Pnt>


<Pnt Name="USD-TRIP.O">
  <Undly ID="EUR-IFXGN.DE" PxStrctTyp="EQ_CORRELATION" IssuDtTm="2018-01-29" LastUpdateTm="2018-01-17"/>
  <Msr Val="0.491733383317429" ValTyp="Other" MktDataTyp="ASK"/>
</Pnt>


<Pnt Name="USD-PYPLV.O">
  <Undly ID="EUR-IFXGN.DE" PxStrctTyp="EQ_CORRELATION" IssuDtTm="2018-01-29" LastUpdateTm="2018-01-24"/>
  <Msr Val="0.481800296671996" ValTyp="Other" MktDataTyp="ASK"/>
</Pnt>


<Pnt Name="USD-TMO.N">
  <Undly ID="EUR-IFXGN.DE" PxStrctTyp="EQ_CORRELATION" IssuDtTm="2018-01-29" LastUpdateTm="2018-01-17"/>
  <Msr Val="0.540807709484655" ValTyp="Other" MktDataTyp="ASK"/>
</Pnt>


<Pnt Name="EUR-AIRP.PA">
  <Undly ID="EUR-IFXGN.DE" PxStrctTyp="EQ_CORRELATION" IssuDtTm="2018-01-29" LastUpdateTm="2018-01-24"/>
  <Msr Val="0.600548000885328" ValTyp="Other" MktDataTyp="ASK"/>
</Pnt>


<Pnt Name="USD-BIDU.O">
  <Undly ID="EUR-IFXGN.DE" PxStrctTyp="EQ_CORRELATION" IssuDtTm="2018-01-29" LastUpdateTm="2018-01-24"/>
  <Msr Val="0.501605781864199" ValTyp="Other" MktDataTyp="ASK"/>
</Pnt>


<Pnt Name="USD-ABX.N">
  <Undly ID="EUR-IFXGN.DE" PxStrctTyp="EQ_CORRELATION" IssuDtTm="2018-01-29" LastUpdateTm="2018-01-24"/>
  <Msr Val="0.311392989265" ValTyp="Other" MktDataTyp="ASK"/>
</Pnt>


<Pnt Name="EUR-SPMIB IND">
  <Undly ID="EUR-IFXGN.DE" PxStrctTyp="EQ_CORRELATION" IssuDtTm="2018-01-29" LastUpdateTm="2018-01-24"/>
  <Msr Val="0.629159712900222" ValTyp="Other" MktDataTyp="ASK"/>
</Pnt>


<Pnt Name="USD-KMB.N">
  <Undly ID="EUR-IFXGN.DE" PxStrctTyp="EQ_CORRELATION" IssuDtTm="2018-01-29" LastUpdateTm="2018-01-24"/>
  <Msr Val="0.409670776745022" ValTyp="Other" MktDataTyp="ASK"/>
</Pnt>


<Pnt Name="USD-ACN.N">
  <Undly ID="EUR-IFXGN.DE" PxStrctTyp="EQ_CORRELATION" IssuDtTm="2018-01-29" LastUpdateTm="2018-01-24"/>
  <Msr Val="0.480977903837438" ValTyp="Other" MktDataTyp="ASK"/>
</Pnt>


<Pnt Name="USD-PPL.N">
  <Undly ID="EUR-IFXGN.DE" PxStrctTyp="EQ_CORRELATION" IssuDtTm="2018-01-29" LastUpdateTm="2018-01-24"/>
  <Msr Val="0.360513570396049" ValTyp="Other" MktDataTyp="ASK"/>
</Pnt>


<Pnt Name="USD-UPS.N">
  <Undly ID="EUR-IFXGN.DE" PxStrctTyp="EQ_CORRELATION" IssuDtTm="2018-01-29" LastUpdateTm="2018-01-17"/>
  <Msr Val="0.489187070144184" ValTyp="Other" MktDataTyp="ASK"/>
</Pnt>


<Pnt Name="USD-AMGN.O">
  <Undly ID="EUR-IFXGN.DE" PxStrctTyp="EQ_CORRELATION" IssuDtTm="2018-01-29" LastUpdateTm="2018-01-24"/>
  <Msr Val="0.492140748000831" ValTyp="Other" MktDataTyp="ASK"/>
</Pnt>


<Pnt Name="USD-WMT.N">
  <Undly ID="EUR-IFXGN.DE" PxStrctTyp="EQ_CORRELATION" IssuDtTm="2018-01-29" LastUpdateTm="2018-01-17"/>
  <Msr Val="0.399784960555099" ValTyp="Other" MktDataTyp="ASK"/>
</Pnt>


<Pnt Name="USD-XLE.N">
  <Undly ID="EUR-IFXGN.DE" PxStrctTyp="EQ_CORRELATION" IssuDtTm="2018-01-29" LastUpdateTm="2018-01-17"/>
  <Msr Val="0.479731151691078" ValTyp="Other" MktDataTyp="ASK"/>
</Pnt>


<Pnt Name="USD-UNP.N">
  <Undly ID="EUR-IFXGN.DE" PxStrctTyp="EQ_CORRELATION" IssuDtTm="2018-01-29" LastUpdateTm="2018-01-17"/>
  <Msr Val="0.518086927909172" ValTyp="Other" MktDataTyp="ASK"/>
</Pnt>


<Pnt Name="USD-BUD.N">
  <Undly ID="EUR-IFXGN.DE" PxStrctTyp="EQ_CORRELATION" IssuDtTm="2018-01-29" LastUpdateTm="2018-01-24"/>
  <Msr Val="0.519697634857053" ValTyp="Other" MktDataTyp="ASK"/>
</Pnt>


<Pnt Name="EUR-RWEG.DE">
  <Undly ID="EUR-IFXGN.DE" PxStrctTyp="EQ_CORRELATION" IssuDtTm="2018-01-29" LastUpdateTm="2018-01-24"/>
  <Msr Val="0.519801945089946" ValTyp="Other" MktDataTyp="ASK"/>
</Pnt>


<Pnt Name="USD-AMX.N">
  <Undly ID="EUR-IFXGN.DE" PxStrctTyp="EQ_CORRELATION" IssuDtTm="2018-01-29" LastUpdateTm="2018-01-24"/>
  <Msr Val="0.452016089004405" ValTyp="Other" MktDataTyp="ASK"/>
</Pnt>


<Pnt Name="USD-TWX.N">
  <Undly ID="EUR-IFXGN.DE" PxStrctTyp="EQ_CORRELATION" IssuDtTm="2018-01-29" LastUpdateTm="2018-01-17"/>
  <Msr Val="0.439939781250754" ValTyp="Other" MktDataTyp="ASK"/>
</Pnt>


<Pnt Name="USD-FDX.N">
  <Undly ID="EUR-IFXGN.DE" PxStrctTyp="EQ_CORRELATION" IssuDtTm="2018-01-29" LastUpdateTm="2018-01-24"/>
  <Msr Val="0.497912822866283" ValTyp="Other" MktDataTyp="ASK"/>
</Pnt>


<Pnt Name="USD-AET.N">
  <Undly ID="EUR-IFXGN.DE" PxStrctTyp="EQ_CORRELATION" IssuDtTm="2018-01-29" LastUpdateTm="2018-01-24"/>
  <Msr Val="0.443471735932539" ValTyp="Other" MktDataTyp="ASK"/>
</Pnt>


<Pnt Name="EUR-IBE.MC">
  <Undly ID="EUR-IFXGN.DE" PxStrctTyp="EQ_CORRELATION" IssuDtTm="2018-01-29" LastUpdateTm="2018-01-24"/>
  <Msr Val="0.536885172419612" ValTyp="Other" MktDataTyp="ASK"/>
</Pnt>


<Pnt Name="GBP-AZN.L">
  <Undly ID="EUR-IFXGN.DE" PxStrctTyp="EQ_CORRELATION" IssuDtTm="2018-01-29" LastUpdateTm="2018-01-24"/>
  <Msr Val="0.447264141027111" ValTyp="Other" MktDataTyp="ASK"/>
</Pnt>


<Pnt Name="USD-DOW.N">
  <Undly ID="EUR-IFXGN.DE" PxStrctTyp="EQ_CORRELATION" IssuDtTm="2018-01-29" LastUpdateTm="2018-01-24"/>
  <Msr Val="0.515113574041908" ValTyp="Other" MktDataTyp="ASK"/>
</Pnt>


<Pnt Name="CHF-SSMI IND">
  <Undly ID="EUR-IFXGN.DE" PxStrctTyp="EQ_CORRELATION" IssuDtTm="2018-01-29" LastUpdateTm="2018-01-24"/>
  <Msr Val="0.624360109677425" ValTyp="Other" MktDataTyp="ASK"/>
</Pnt>


<Pnt Name="USD-EBAY.O">
  <Undly ID="EUR-IFXGN.DE" PxStrctTyp="EQ_CORRELATION" IssuDtTm="2018-01-29" LastUpdateTm="2018-01-24"/>
  <Msr Val="0.485577542827121" ValTyp="Other" MktDataTyp="ASK"/>
</Pnt>


<Pnt Name="CHF-NOVZN.S">
  <Undly ID="EUR-IFXGN.DE" PxStrctTyp="EQ_CORRELATION" IssuDtTm="2018-01-29" LastUpdateTm="2018-01-24"/>
  <Msr Val="0.504962203413792" ValTyp="Other" MktDataTyp="ASK"/>
</Pnt>


<Pnt Name="USD-PSX.N">
  <Undly ID="EUR-IFXGN.DE" PxStrctTyp="EQ_CORRELATION" IssuDtTm="2018-01-29" LastUpdateTm="2018-01-24"/>
  <Msr Val="0.462100581291796" ValTyp="Other" MktDataTyp="ASK"/>
</Pnt>


<Pnt Name="SEK-ERICB.ST">
  <Undly ID="EUR-IFXGN.DE" PxStrctTyp="EQ_CORRELATION" IssuDtTm="2018-01-29" LastUpdateTm="2018-01-24"/>
  <Msr Val="0.591527205022958" ValTyp="Other" MktDataTyp="ASK"/>
</Pnt>


<Pnt Name="USD-WYNN.O">
  <Undly ID="EUR-IFXGN.DE" PxStrctTyp="EQ_CORRELATION" IssuDtTm="2018-01-29" LastUpdateTm="2018-01-17"/>
  <Msr Val="0.446431024733329" ValTyp="Other" MktDataTyp="ASK"/>
</Pnt>


<Pnt Name="EUR-GDFPP.PA">
  <Undly ID="EUR-IFXGN.DE" PxStrctTyp="EQ_CORRELATION" IssuDtTm="2018-01-29" LastUpdateTm="2018-01-24"/>
  <Msr Val="0.549948574260868" ValTyp="Other" MktDataTyp="ASK"/>
</Pnt>


<Pnt Name="HSCEI IND">
  <Undly ID="EUR-IFXGN.DE" PxStrctTyp="EQ_CORRELATION" IssuDtTm="2018-01-29" LastUpdateTm="2018-01-24"/>
  <Msr Val="0.471878367371744" ValTyp="Other" MktDataTyp="ASK"/>
</Pnt>


<Pnt Name="USD-XOP.N">
  <Undly ID="EUR-IFXGN.DE" PxStrctTyp="EQ_CORRELATION" IssuDtTm="2018-01-29" LastUpdateTm="2018-01-17"/>
  <Msr Val="0.448031025430745" ValTyp="Other" MktDataTyp="ASK"/>
</Pnt>


<Pnt Name="USD-PG.N">
  <Undly ID="EUR-IFXGN.DE" PxStrctTyp="EQ_CORRELATION" IssuDtTm="2018-01-29" LastUpdateTm="2018-01-24"/>
  <Msr Val="0.403545057304961" ValTyp="Other" MktDataTyp="ASK"/>
</Pnt>


<Pnt Name="USD-XLY.N">
  <Undly ID="EUR-IFXGN.DE" PxStrctTyp="EQ_CORRELATION" IssuDtTm="2018-01-29" LastUpdateTm="2018-01-17"/>
  <Msr Val="0.598445254239966" ValTyp="Other" MktDataTyp="ASK"/>
</Pnt>


<Pnt Name="USD-BAC.N">
  <Undly ID="EUR-IFXGN.DE" PxStrctTyp="EQ_CORRELATION" IssuDtTm="2018-01-29" LastUpdateTm="2018-01-24"/>
  <Msr Val="0.526406428182468" ValTyp="Other" MktDataTyp="ASK"/>
</Pnt>


<Pnt Name="USD-QCOM.O">
  <Undly ID="EUR-IFXGN.DE" PxStrctTyp="EQ_CORRELATION" IssuDtTm="2018-01-29" LastUpdateTm="2018-01-24"/>
  <Msr Val="0.51162655759241" ValTyp="Other" MktDataTyp="ASK"/>
</Pnt>


<Pnt Name="EUR-FREG.DE">
  <Undly ID="EUR-IFXGN.DE" PxStrctTyp="EQ_CORRELATION" IssuDtTm="2018-01-29" LastUpdateTm="2018-01-24"/>
  <Msr Val="0.57930904175593" ValTyp="Other" MktDataTyp="ASK"/>
</Pnt>


<Pnt Name="CHF-NESN.S">
  <Undly ID="EUR-IFXGN.DE" PxStrctTyp="EQ_CORRELATION" IssuDtTm="2018-01-29" LastUpdateTm="2018-01-24"/>
  <Msr Val="0.52125169376345" ValTyp="Other" MktDataTyp="ASK"/>
</Pnt>


<Pnt Name="USD-JPM.N">
  <Undly ID="EUR-IFXGN.DE" PxStrctTyp="EQ_CORRELATION" IssuDtTm="2018-01-29" LastUpdateTm="2018-01-24"/>
  <Msr Val="0.559356995024942" ValTyp="Other" MktDataTyp="ASK"/>
</Pnt>


<Pnt Name="EUR-LIN.DE">
  <Undly ID="EUR-IFXGN.DE" PxStrctTyp="EQ_CORRELATION" IssuDtTm="2018-01-29" LastUpdateTm="2018-01-24"/>
  <Msr Val="0.618377588040157" ValTyp="Other" MktDataTyp="ASK"/>
</Pnt>


<Pnt Name="EUR-IBEX 35 IND">
  <Undly ID="EUR-IFXGN.DE" PxStrctTyp="EQ_CORRELATION" IssuDtTm="2018-01-29" LastUpdateTm="2018-01-24"/>
  <Msr Val="0.627019079037275" ValTyp="Other" MktDataTyp="ASK"/>
</Pnt>


<Pnt Name="USD-SYMC.O">
  <Undly ID="EUR-IFXGN.DE" PxStrctTyp="EQ_CORRELATION" IssuDtTm="2018-01-29" LastUpdateTm="2018-01-17"/>
  <Msr Val="0.516362755723941" ValTyp="Other" MktDataTyp="ASK"/>
</Pnt>


<Pnt Name="USD-XLI.N">
  <Undly ID="EUR-IFXGN.DE" PxStrctTyp="EQ_CORRELATION" IssuDtTm="2018-01-29" LastUpdateTm="2018-01-17"/>
  <Msr Val="0.609156067377892" ValTyp="Other" MktDataTyp="ASK"/>
</Pnt>


<Pnt Name="USD-COH.N">
  <Undly ID="EUR-IFXGN.DE" PxStrctTyp="EQ_CORRELATION" IssuDtTm="2018-01-29" LastUpdateTm="2018-01-24"/>
  <Msr Val="0.441146971634862" ValTyp="Other" MktDataTyp="ASK"/>
</Pnt>


<Pnt Name="EUR-BMW.DE">
  <Undly ID="EUR-IFXGN.DE" PxStrctTyp="EQ_CORRELATION" IssuDtTm="2018-01-29" LastUpdateTm="2018-01-24"/>
  <Msr Val="0.642420629503626" ValTyp="Other" MktDataTyp="ASK"/>
</Pnt>


<Pnt Name="EUR-UNBP.AS">
  <Undly ID="EUR-IFXGN.DE" PxStrctTyp="EQ_CORRELATION" IssuDtTm="2018-01-29" LastUpdateTm="2018-01-24"/>
  <Msr Val="0.564573955660305" ValTyp="Other" MktDataTyp="ASK"/>
</Pnt>


<Pnt Name="CAD-TSX60.IND">
  <Undly ID="EUR-IFXGN.DE" PxStrctTyp="EQ_CORRELATION" IssuDtTm="2018-01-29" LastUpdateTm="2018-01-24"/>
  <Msr Val="0.551993712425755" ValTyp="Other" MktDataTyp="ASK"/>
</Pnt>


<Pnt Name="USD-VIAB.N">
  <Undly ID="EUR-IFXGN.DE" PxStrctTyp="EQ_CORRELATION" IssuDtTm="2018-01-29" LastUpdateTm="2018-01-17"/>
  <Msr Val="0.467393981530157" ValTyp="Other" MktDataTyp="ASK"/>
</Pnt>


<Pnt Name="EUR-TIT.MI">
  <Undly ID="EUR-IFXGN.DE" PxStrctTyp="EQ_CORRELATION" IssuDtTm="2018-01-29" LastUpdateTm="2018-01-24"/>
  <Msr Val="0.543353401327824" ValTyp="Other" MktDataTyp="ASK"/>
</Pnt>


<Pnt Name="USD-AMT.N">
  <Undly ID="EUR-IFXGN.DE" PxStrctTyp="EQ_CORRELATION" IssuDtTm="2018-01-29" LastUpdateTm="2018-01-24"/>
  <Msr Val="0.41949503525566" ValTyp="Other" MktDataTyp="ASK"/>
</Pnt>


<Pnt Name="USD-PNC.N">
  <Undly ID="EUR-IFXGN.DE" PxStrctTyp="EQ_CORRELATION" IssuDtTm="2018-01-29" LastUpdateTm="2018-01-24"/>
  <Msr Val="0.523054637919344" ValTyp="Other" MktDataTyp="ASK"/>
</Pnt>


<Pnt Name="USD-AIG.N">
  <Undly ID="EUR-IFXGN.DE" PxStrctTyp="EQ_CORRELATION" IssuDtTm="2018-01-29" LastUpdateTm="2018-01-24"/>
  <Msr Val="0.528155732838295" ValTyp="Other" MktDataTyp="ASK"/>
</Pnt>


<Pnt Name="USD-NKE.N">
  <Undly ID="EUR-IFXGN.DE" PxStrctTyp="EQ_CORRELATION" IssuDtTm="2018-01-29" LastUpdateTm="2018-01-24"/>
  <Msr Val="0.482411315751936" ValTyp="Other" MktDataTyp="ASK"/>
</Pnt>


<Pnt Name="USD-XLK.N">
  <Undly ID="EUR-IFXGN.DE" PxStrctTyp="EQ_CORRELATION" IssuDtTm="2018-01-29" LastUpdateTm="2018-01-17"/>
  <Msr Val="0.624316777439147" ValTyp="Other" MktDataTyp="ASK"/>
</Pnt>


<Pnt Name="EUR-CRDI.MI">
  <Undly ID="EUR-IFXGN.DE" PxStrctTyp="EQ_CORRELATION" IssuDtTm="2018-01-29" LastUpdateTm="2018-01-24"/>
  <Msr Val="0.516572440416215" ValTyp="Other" MktDataTyp="ASK"/>
</Pnt>


<Pnt Name="USD-MELI.O">
  <Undly ID="EUR-IFXGN.DE" PxStrctTyp="EQ_CORRELATION" IssuDtTm="2018-01-29" LastUpdateTm="2018-01-24"/>
  <Msr Val="0.507104175176924" ValTyp="Other" MktDataTyp="ASK"/>
</Pnt>


<Pnt Name="CHF-CSGN.S">
  <Undly ID="EUR-IFXGN.DE" PxStrctTyp="EQ_CORRELATION" IssuDtTm="2018-01-29" LastUpdateTm="2018-01-24"/>
  <Msr Val="0.547435497615747" ValTyp="Other" MktDataTyp="ASK"/>
</Pnt>


<Pnt Name="USD-MET.N">
  <Undly ID="EUR-IFXGN.DE" PxStrctTyp="EQ_CORRELATION" IssuDtTm="2018-01-29" LastUpdateTm="2018-01-24"/>
  <Msr Val="0.549296728163599" ValTyp="Other" MktDataTyp="ASK"/>
</Pnt>


<Pnt Name="EUR-VOWG_P.DE">
  <Undly ID="EUR-IFXGN.DE" PxStrctTyp="EQ_CORRELATION" IssuDtTm="2018-01-29" LastUpdateTm="2018-01-24"/>
  <Msr Val="0.61250368886694" ValTyp="Other" MktDataTyp="ASK"/>
</Pnt>


<Pnt Name="USD-SCHW.N">
  <Undly ID="EUR-IFXGN.DE" PxStrctTyp="EQ_CORRELATION" IssuDtTm="2018-01-29" LastUpdateTm="2018-01-17"/>
  <Msr Val="0.54207431934813" ValTyp="Other" MktDataTyp="ASK"/>
</Pnt>


<Pnt Name="USD-V.N">
  <Undly ID="EUR-IFXGN.DE" PxStrctTyp="EQ_CORRELATION" IssuDtTm="2018-01-29" LastUpdateTm="2018-01-17"/>
  <Msr Val="0.503133021013606" ValTyp="Other" MktDataTyp="ASK"/>
</Pnt>


<Pnt Name="USD-NDX 100 IND">
  <Undly ID="EUR-IFXGN.DE" PxStrctTyp="EQ_CORRELATION" IssuDtTm="2018-01-29" LastUpdateTm="2018-01-24"/>
  <Msr Val="0.631602173460882" ValTyp="Other" MktDataTyp="ASK"/>
</Pnt>


<Pnt Name="USD-KR.N">
  <Undly ID="EUR-IFXGN.DE" PxStrctTyp="EQ_CORRELATION" IssuDtTm="2018-01-29" LastUpdateTm="2018-01-24"/>
  <Msr Val="0.41037583821727" ValTyp="Other" MktDataTyp="ASK"/>
</Pnt>


<Pnt Name="USD-JWN.N">
  <Undly ID="EUR-IFXGN.DE" PxStrctTyp="EQ_CORRELATION" IssuDtTm="2018-01-29" LastUpdateTm="2018-01-24"/>
  <Msr Val="0.429268947454042" ValTyp="Other" MktDataTyp="ASK"/>
</Pnt>


<Pnt Name="USD-PM.N">
  <Undly ID="EUR-IFXGN.DE" PxStrctTyp="EQ_CORRELATION" IssuDtTm="2018-01-29" LastUpdateTm="2018-01-24"/>
  <Msr Val="0.404600254658935" ValTyp="Other" MktDataTyp="ASK"/>
</Pnt>


<Pnt Name="USD-HAL.N">
  <Undly ID="EUR-IFXGN.DE" PxStrctTyp="EQ_CORRELATION" IssuDtTm="2018-01-29" LastUpdateTm="2018-01-24"/>
  <Msr Val="0.441762952939023" ValTyp="Other" MktDataTyp="ASK"/>
</Pnt>


<Pnt Name="GBP-BT.L">
  <Undly ID="EUR-IFXGN.DE" PxStrctTyp="EQ_CORRELATION" IssuDtTm="2018-01-29" LastUpdateTm="2018-01-24"/>
  <Msr Val="0.482865772544495" ValTyp="Other" MktDataTyp="ASK"/>
</Pnt>


<Pnt Name="USD-WAG.N">
  <Undly ID="EUR-IFXGN.DE" PxStrctTyp="EQ_CORRELATION" IssuDtTm="2018-01-29" LastUpdateTm="2018-01-17"/>
  <Msr Val="0.447550635838987" ValTyp="Other" MktDataTyp="ASK"/>
</Pnt>


<Pnt Name="USD-NFLX.OQ">
  <Undly ID="EUR-IFXGN.DE" PxStrctTyp="EQ_CORRELATION" IssuDtTm="2018-01-29" LastUpdateTm="2018-01-24"/>
  <Msr Val="0.448239849905012" ValTyp="Other" MktDataTyp="ASK"/>
</Pnt>


<Pnt Name="USD-GE.N">
  <Undly ID="EUR-IFXGN.DE" PxStrctTyp="EQ_CORRELATION" IssuDtTm="2018-01-29" LastUpdateTm="2018-01-24"/>
  <Msr Val="0.516551266203549" ValTyp="Other" MktDataTyp="ASK"/>
</Pnt>


<Pnt Name="USD-SPG.N">
  <Undly ID="EUR-IFXGN.DE" PxStrctTyp="EQ_CORRELATION" IssuDtTm="2018-01-29" LastUpdateTm="2018-01-17"/>
  <Msr Val="0.424712683203429" ValTyp="Other" MktDataTyp="ASK"/>
</Pnt>


<Pnt Name="EUR-LHA.DE">
  <Undly ID="EUR-IFXGN.DE" PxStrctTyp="EQ_CORRELATION" IssuDtTm="2018-01-29" LastUpdateTm="2018-01-24"/>
  <Msr Val="0.552973611585858" ValTyp="Other" MktDataTyp="ASK"/>
</Pnt>


<Pnt Name="GBP-GLEN.L">
  <Undly ID="EUR-IFXGN.DE" PxStrctTyp="EQ_CORRELATION" IssuDtTm="2018-01-29" LastUpdateTm="2018-01-24"/>
  <Msr Val="0.444567540987502" ValTyp="Other" MktDataTyp="ASK"/>
</Pnt>


<Pnt Name="USD-INCY.O">
  <Undly ID="EUR-IFXGN.DE" PxStrctTyp="EQ_CORRELATION" IssuDtTm="2018-01-29" LastUpdateTm="2018-01-24"/>
  <Msr Val="0.450736657674002" ValTyp="Other" MktDataTyp="ASK"/>
</Pnt>


<Pnt Name="EUR-CAGR.PA">
  <Undly ID="EUR-IFXGN.DE" PxStrctTyp="EQ_CORRELATION" IssuDtTm="2018-01-29" LastUpdateTm="2018-01-24"/>
  <Msr Val="0.584137628256419" ValTyp="Other" MktDataTyp="ASK"/>
</Pnt>


<Pnt Name="USD-T.N">
  <Undly ID="EUR-IFXGN.DE" PxStrctTyp="EQ_CORRELATION" IssuDtTm="2018-01-29" LastUpdateTm="2018-01-17"/>
  <Msr Val="0.372265475376821" ValTyp="Other" MktDataTyp="ASK"/>
</Pnt>


<Pnt Name="USD-EXPE.O">
  <Undly ID="EUR-IFXGN.DE" PxStrctTyp="EQ_CORRELATION" IssuDtTm="2018-01-29" LastUpdateTm="2018-01-24"/>
  <Msr Val="0.497443884071933" ValTyp="Other" MktDataTyp="ASK"/>
</Pnt>


<Pnt Name="USD-HD.N">
  <Undly ID="EUR-IFXGN.DE" PxStrctTyp="EQ_CORRELATION" IssuDtTm="2018-01-29" LastUpdateTm="2018-01-24"/>
  <Msr Val="0.498443692206222" ValTyp="Other" MktDataTyp="ASK"/>
</Pnt>


<Pnt Name="GBP-FTSE IND">
  <Undly ID="EUR-IFXGN.DE" PxStrctTyp="EQ_CORRELATION" IssuDtTm="2018-01-29" LastUpdateTm="2018-01-24"/>
  <Msr Val="0.625343510001284" ValTyp="Other" MktDataTyp="ASK"/>
</Pnt>


<Pnt Name="USD-D.N">
  <Undly ID="EUR-IFXGN.DE" PxStrctTyp="EQ_CORRELATION" IssuDtTm="2018-01-29" LastUpdateTm="2018-01-24"/>
  <Msr Val="0.360886409669438" ValTyp="Other" MktDataTyp="ASK"/>
</Pnt>


<Pnt Name="USD-CELG.O">
  <Undly ID="EUR-IFXGN.DE" PxStrctTyp="EQ_CORRELATION" IssuDtTm="2018-01-29" LastUpdateTm="2018-01-24"/>
  <Msr Val="0.489799764944486" ValTyp="Other" MktDataTyp="ASK"/>
</Pnt>


<Pnt Name="USD-MPC.N">
  <Undly ID="EUR-IFXGN.DE" PxStrctTyp="EQ_CORRELATION" IssuDtTm="2018-01-29" LastUpdateTm="2018-01-24"/>
  <Msr Val="0.432472294008639" ValTyp="Other" MktDataTyp="ASK"/>
</Pnt>


<Pnt Name="USD-DIS.N">
  <Undly ID="EUR-IFXGN.DE" PxStrctTyp="EQ_CORRELATION" IssuDtTm="2018-01-29" LastUpdateTm="2018-01-24"/>
  <Msr Val="0.46887679048522" ValTyp="Other" MktDataTyp="ASK"/>
</Pnt>


<Pnt Name="EUR-ASML.AS">
  <Undly ID="EUR-IFXGN.DE" PxStrctTyp="EQ_CORRELATION" IssuDtTm="2018-01-29" LastUpdateTm="2018-01-24"/>
  <Msr Val="0.689377519105864" ValTyp="Other" MktDataTyp="ASK"/>
</Pnt>


<Pnt Name="EUR-TOTF.PA">
  <Undly ID="EUR-IFXGN.DE" PxStrctTyp="EQ_CORRELATION" IssuDtTm="2018-01-29" LastUpdateTm="2018-01-24"/>
  <Msr Val="0.54960231952242" ValTyp="Other" MktDataTyp="ASK"/>
</Pnt>


<Pnt Name="EUR-TKAG.DE">
  <Undly ID="EUR-IFXGN.DE" PxStrctTyp="EQ_CORRELATION" IssuDtTm="2018-01-29" LastUpdateTm="2018-01-24"/>
  <Msr Val="0.620736611332353" ValTyp="Other" MktDataTyp="ASK"/>
</Pnt>


<Pnt Name="EUROSTOXX50 IND">
  <Undly ID="EUR-IFXGN.DE" PxStrctTyp="EQ_CORRELATION" IssuDtTm="2018-01-29" LastUpdateTm="2018-01-24"/>
  <Msr Val="0.680433265012364" ValTyp="Other" MktDataTyp="ASK"/>
</Pnt>


<Pnt Name="EUR-ENI.MI">
  <Undly ID="EUR-IFXGN.DE" PxStrctTyp="EQ_CORRELATION" IssuDtTm="2018-01-29" LastUpdateTm="2018-01-24"/>
  <Msr Val="0.534085804739913" ValTyp="Other" MktDataTyp="ASK"/>
</Pnt>


<Pnt Name="SEK-VOLVB.ST">
  <Undly ID="EUR-IFXGN.DE" PxStrctTyp="EQ_CORRELATION" IssuDtTm="2018-01-29" LastUpdateTm="2018-01-24"/>
  <Msr Val="0.574643903096908" ValTyp="Other" MktDataTyp="ASK"/>
</Pnt>


<Pnt Name="USD-AMAT.O">
  <Undly ID="EUR-IFXGN.DE" PxStrctTyp="EQ_CORRELATION" IssuDtTm="2018-01-29" LastUpdateTm="2018-01-24"/>
  <Msr Val="0.602184772156862" ValTyp="Other" MktDataTyp="ASK"/>
</Pnt>


<Pnt Name="USD-KRFTV.O">
  <Undly ID="EUR-IFXGN.DE" PxStrctTyp="EQ_CORRELATION" IssuDtTm="2018-01-29" LastUpdateTm="2018-01-24"/>
  <Msr Val="0.447094921167599" ValTyp="Other" MktDataTyp="ASK"/>
</Pnt>


<Pnt Name="USD-XLP.N">
  <Undly ID="EUR-IFXGN.DE" PxStrctTyp="EQ_CORRELATION" IssuDtTm="2018-01-29" LastUpdateTm="2018-01-17"/>
  <Msr Val="0.49754469224759" ValTyp="Other" MktDataTyp="ASK"/>
</Pnt>


<Pnt Name="USD-KORS.N">
  <Undly ID="EUR-IFXGN.DE" PxStrctTyp="EQ_CORRELATION" IssuDtTm="2018-01-29" LastUpdateTm="2018-01-24"/>
  <Msr Val="0.451025020390791" ValTyp="Other" MktDataTyp="ASK"/>
</Pnt>


<Pnt Name="GBP-PRU.L">
  <Undly ID="EUR-IFXGN.DE" PxStrctTyp="EQ_CORRELATION" IssuDtTm="2018-01-29" LastUpdateTm="2018-01-24"/>
  <Msr Val="0.557764792950736" ValTyp="Other" MktDataTyp="ASK"/>
</Pnt>


<Pnt Name="EUR-BASF.DE">
  <Undly ID="EUR-IFXGN.DE" PxStrctTyp="EQ_CORRELATION" IssuDtTm="2018-01-29" LastUpdateTm="2018-01-24"/>
  <Msr Val="0.666009193539838" ValTyp="Other" MktDataTyp="ASK"/>
</Pnt>


<Pnt Name="USD-ABBV-W.N">
  <Undly ID="EUR-IFXGN.DE" PxStrctTyp="EQ_CORRELATION" IssuDtTm="2018-01-29" LastUpdateTm="2018-01-24"/>
  <Msr Val="0.446008787786674" ValTyp="Other" MktDataTyp="ASK"/>
</Pnt>


<Pnt Name="USD-HYG.P">
  <Undly ID="EUR-IFXGN.DE" PxStrctTyp="EQ_CORRELATION" IssuDtTm="2018-01-29" LastUpdateTm="2018-01-24"/>
  <Msr Val="0.524253092556706" ValTyp="Other" MktDataTyp="ASK"/>
</Pnt>


<Pnt Name="GBP-VOD.L">
  <Undly ID="EUR-IFXGN.DE" PxStrctTyp="EQ_CORRELATION" IssuDtTm="2018-01-29" LastUpdateTm="2018-01-24"/>
  <Msr Val="0.484251847459518" ValTyp="Other" MktDataTyp="ASK"/>
</Pnt>


<Pnt Name="USD-SLB.N">
  <Undly ID="EUR-IFXGN.DE" PxStrctTyp="EQ_CORRELATION" IssuDtTm="2018-01-29" LastUpdateTm="2018-01-17"/>
  <Msr Val="0.472433834689742" ValTyp="Other" MktDataTyp="ASK"/>
</Pnt>


<Pnt Name="AS51 IND">
  <Undly ID="EUR-IFXGN.DE" PxStrctTyp="EQ_CORRELATION" IssuDtTm="2018-01-29" LastUpdateTm="2018-01-24"/>
  <Msr Val="0.538914087843958" ValTyp="Other" MktDataTyp="ASK"/>
</Pnt>


<Pnt Name="CHF-UBSG.S">
  <Undly ID="EUR-IFXGN.DE" PxStrctTyp="EQ_CORRELATION" IssuDtTm="2018-01-29" LastUpdateTm="2018-01-24"/>
  <Msr Val="0.579575667368094" ValTyp="Other" MktDataTyp="ASK"/>
</Pnt>


<Pnt Name="EUR-DPW.DE">
  <Undly ID="EUR-IFXGN.DE" PxStrctTyp="EQ_CORRELATION" IssuDtTm="2018-01-29" LastUpdateTm="2018-01-24"/>
  <Msr Val="0.647715526566304" ValTyp="Other" MktDataTyp="ASK"/>
</Pnt>


<Pnt Name="USD-GD.N">
  <Undly ID="EUR-IFXGN.DE" PxStrctTyp="EQ_CORRELATION" IssuDtTm="2018-01-29" LastUpdateTm="2018-01-24"/>
  <Msr Val="0.494844768196895" ValTyp="Other" MktDataTyp="ASK"/>
</Pnt>


<Pnt Name="CHF-SRENH.S">
  <Undly ID="EUR-IFXGN.DE" PxStrctTyp="EQ_CORRELATION" IssuDtTm="2018-01-29" LastUpdateTm="2018-01-24"/>
  <Msr Val="0.571341008126364" ValTyp="Other" MktDataTyp="ASK"/>
</Pnt>


<Pnt Name="EUR-SCHN.PA">
  <Undly ID="EUR-IFXGN.DE" PxStrctTyp="EQ_CORRELATION" IssuDtTm="2018-01-29" LastUpdateTm="2018-01-24"/>
  <Msr Val="0.628458284265965" ValTyp="Other" MktDataTyp="ASK"/>
</Pnt>


<Pnt Name="USD-PCAR.O">
  <Undly ID="EUR-IFXGN.DE" PxStrctTyp="EQ_CORRELATION" IssuDtTm="2018-01-29" LastUpdateTm="2018-01-24"/>
  <Msr Val="0.53011188391956" ValTyp="Other" MktDataTyp="ASK"/>
</Pnt>


<Pnt Name="USD-CHTR.O">
  <Undly ID="EUR-IFXGN.DE" PxStrctTyp="EQ_CORRELATION" IssuDtTm="2018-01-29" LastUpdateTm="2018-01-24"/>
  <Msr Val="0.429866461261607" ValTyp="Other" MktDataTyp="ASK"/>
</Pnt>


<Pnt Name="USD-MMM.N">
  <Undly ID="EUR-IFXGN.DE" PxStrctTyp="EQ_CORRELATION" IssuDtTm="2018-01-29" LastUpdateTm="2018-01-24"/>
  <Msr Val="0.551024890695935" ValTyp="Other" MktDataTyp="ASK"/>
</Pnt>


<Pnt Name="USD-AMD.N">
  <Undly ID="EUR-IFXGN.DE" PxStrctTyp="EQ_CORRELATION" IssuDtTm="2018-01-29" LastUpdateTm="2018-01-24"/>
  <Msr Val="0.4947683368433" ValTyp="Other" MktDataTyp="ASK"/>
</Pnt>


<Pnt Name="USD-USB.N">
  <Undly ID="EUR-IFXGN.DE" PxStrctTyp="EQ_CORRELATION" IssuDtTm="2018-01-29" LastUpdateTm="2018-01-17"/>
  <Msr Val="0.53431436796129" ValTyp="Other" MktDataTyp="ASK"/>
</Pnt>


<Pnt Name="EUR-RENA.PA">
  <Undly ID="EUR-IFXGN.DE" PxStrctTyp="EQ_CORRELATION" IssuDtTm="2018-01-29" LastUpdateTm="2018-01-24"/>
  <Msr Val="0.622111052186023" ValTyp="Other" MktDataTyp="ASK"/>
</Pnt>


<Pnt Name="USD-CVS.N">
  <Undly ID="EUR-IFXGN.DE" PxStrctTyp="EQ_CORRELATION" IssuDtTm="2018-01-29" LastUpdateTm="2018-01-24"/>
  <Msr Val="0.443223198113535" ValTyp="Other" MktDataTyp="ASK"/>
</Pnt>


<Pnt Name="EUR-AHLN.AS">
  <Undly ID="EUR-IFXGN.DE" PxStrctTyp="EQ_CORRELATION" IssuDtTm="2018-01-29" LastUpdateTm="2018-01-24"/>
  <Msr Val="0.52013748516886" ValTyp="Other" MktDataTyp="ASK"/>
</Pnt>


<Pnt Name="EUR-MUVGN.DE">
  <Undly ID="EUR-IFXGN.DE" PxStrctTyp="EQ_CORRELATION" IssuDtTm="2018-01-29" LastUpdateTm="2018-01-24"/>
  <Msr Val="0.615256684808515" ValTyp="Other" MktDataTyp="ASK"/>
</Pnt>


<Pnt Name="EUR-GASI.MI">
  <Undly ID="EUR-IFXGN.DE" PxStrctTyp="EQ_CORRELATION" IssuDtTm="2018-01-29" LastUpdateTm="2018-01-24"/>
  <Msr Val="0.573262128556545" ValTyp="Other" MktDataTyp="ASK"/>
</Pnt>


<Pnt Name="USD-FXI.N">
  <Undly ID="EUR-IFXGN.DE" PxStrctTyp="EQ_CORRELATION" IssuDtTm="2018-01-29" LastUpdateTm="2018-01-24"/>
  <Msr Val="0.535678034807555" ValTyp="Other" MktDataTyp="ASK"/>
</Pnt>


<Pnt Name="GBP-HSBA.L">
  <Undly ID="EUR-IFXGN.DE" PxStrctTyp="EQ_CORRELATION" IssuDtTm="2018-01-29" LastUpdateTm="2018-01-24"/>
  <Msr Val="0.504738986126825" ValTyp="Other" MktDataTyp="ASK"/>
</Pnt>


<Pnt Name="USD-APA.N">
  <Undly ID="EUR-IFXGN.DE" PxStrctTyp="EQ_CORRELATION" IssuDtTm="2018-01-29" LastUpdateTm="2018-01-24"/>
  <Msr Val="0.426511646929496" ValTyp="Other" MktDataTyp="ASK"/>
</Pnt>


<Pnt Name="USD-EOG.N">
  <Undly ID="EUR-IFXGN.DE" PxStrctTyp="EQ_CORRELATION" IssuDtTm="2018-01-29" LastUpdateTm="2018-01-24"/>
  <Msr Val="0.42242786024087" ValTyp="Other" MktDataTyp="ASK"/>
</Pnt>


<Pnt Name="USD-ORCL.O">
  <Undly ID="EUR-IFXGN.DE" PxStrctTyp="EQ_CORRELATION" IssuDtTm="2018-01-29" LastUpdateTm="2018-01-24"/>
  <Msr Val="0.49934316346357" ValTyp="Other" MktDataTyp="ASK"/>
</Pnt>


<Pnt Name="CHF-SCMN.S">
  <Undly ID="EUR-IFXGN.DE" PxStrctTyp="EQ_CORRELATION" IssuDtTm="2018-01-29" LastUpdateTm="2018-01-24"/>
  <Msr Val="0.519796331710779" ValTyp="Other" MktDataTyp="ASK"/>
</Pnt>


<Pnt Name="EUR-ADSGN.DE">
  <Undly ID="EUR-IFXGN.DE" PxStrctTyp="EQ_CORRELATION" IssuDtTm="2018-01-29" LastUpdateTm="2018-01-24"/>
  <Msr Val="0.523226196012108" ValTyp="Other" MktDataTyp="ASK"/>
</Pnt>


<Pnt Name="USD-GOOG.O">
  <Undly ID="EUR-IFXGN.DE" PxStrctTyp="EQ_CORRELATION" IssuDtTm="2018-01-29" LastUpdateTm="2018-01-24"/>
  <Msr Val="0.533766694464062" ValTyp="Other" MktDataTyp="ASK"/>
</Pnt>


<Pnt Name="USD-CSX.N">
  <Undly ID="EUR-IFXGN.DE" PxStrctTyp="EQ_CORRELATION" IssuDtTm="2018-01-29" LastUpdateTm="2018-01-24"/>
  <Msr Val="0.522445646078129" ValTyp="Other" MktDataTyp="ASK"/>
</Pnt>


<Pnt Name="EUR-DANO.PA">
  <Undly ID="EUR-IFXGN.DE" PxStrctTyp="EQ_CORRELATION" IssuDtTm="2018-01-29" LastUpdateTm="2018-01-24"/>
  <Msr Val="0.556004472937554" ValTyp="Other" MktDataTyp="ASK"/>
</Pnt>


<Pnt Name="USD-HAS.N">
  <Undly ID="EUR-IFXGN.DE" PxStrctTyp="EQ_CORRELATION" IssuDtTm="2018-01-29" LastUpdateTm="2018-01-24"/>
  <Msr Val="0.45684986375138" ValTyp="Other" MktDataTyp="ASK"/>
</Pnt>


<Pnt Name="GBP-BLT.L">
  <Undly ID="EUR-IFXGN.DE" PxStrctTyp="EQ_CORRELATION" IssuDtTm="2018-01-29" LastUpdateTm="2018-01-24"/>
  <Msr Val="0.462253198559786" ValTyp="Other" MktDataTyp="ASK"/>
</Pnt>


<Pnt Name="USD-IBB.O">
  <Undly ID="EUR-IFXGN.DE" PxStrctTyp="EQ_CORRELATION" IssuDtTm="2018-01-29" LastUpdateTm="2018-01-24"/>
  <Msr Val="0.519517656817266" ValTyp="Other" MktDataTyp="ASK"/>
</Pnt>


<Pnt Name="EUR-LVMH.PA">
  <Undly ID="EUR-IFXGN.DE" PxStrctTyp="EQ_CORRELATION" IssuDtTm="2018-01-29" LastUpdateTm="2018-01-24"/>
  <Msr Val="0.601935433592713" ValTyp="Other" MktDataTyp="ASK"/>
</Pnt>


<Pnt Name="USD-CB.N">
  <Undly ID="EUR-IFXGN.DE" PxStrctTyp="EQ_CORRELATION" IssuDtTm="2018-01-29" LastUpdateTm="2018-01-24"/>
  <Msr Val="0.484595595150075" ValTyp="Other" MktDataTyp="ASK"/>
</Pnt>


<Pnt Name="USD-XLU.N">
  <Undly ID="EUR-IFXGN.DE" PxStrctTyp="EQ_CORRELATION" IssuDtTm="2018-01-29" LastUpdateTm="2018-01-17"/>
  <Msr Val="0.346473057181076" ValTyp="Other" MktDataTyp="ASK"/>
</Pnt>


<Pnt Name="USD-WLP.N">
  <Undly ID="EUR-IFXGN.DE" PxStrctTyp="EQ_CORRELATION" IssuDtTm="2018-01-29" LastUpdateTm="2018-01-17"/>
  <Msr Val="0.436349031872265" ValTyp="Other" MktDataTyp="ASK"/>
</Pnt>


<Pnt Name="EUR-EAUG.PA">
  <Undly ID="EUR-IFXGN.DE" PxStrctTyp="EQ_CORRELATION" IssuDtTm="2018-01-29" LastUpdateTm="2018-01-24"/>
  <Msr Val="0.548570056294498" ValTyp="Other" MktDataTyp="ASK"/>
</Pnt>


<Pnt Name="USD-COF.N">
  <Undly ID="EUR-IFXGN.DE" PxStrctTyp="EQ_CORRELATION" IssuDtTm="2018-01-29" LastUpdateTm="2018-01-24"/>
  <Msr Val="0.506605032291159" ValTyp="Other" MktDataTyp="ASK"/>
</Pnt>


<Pnt Name="EUR-UNC.AS">
  <Undly ID="EUR-IFXGN.DE" PxStrctTyp="EQ_CORRELATION" IssuDtTm="2018-01-29" LastUpdateTm="2018-01-24"/>
  <Msr Val="0.566427442013607" ValTyp="Other" MktDataTyp="ASK"/>
</Pnt>


<Pnt Name="USD-BBD.N">
  <Undly ID="EUR-IFXGN.DE" PxStrctTyp="EQ_CORRELATION" IssuDtTm="2018-01-29" LastUpdateTm="2018-01-24"/>
  <Msr Val="0.412222080217864" ValTyp="Other" MktDataTyp="ASK"/>
</Pnt>


<Pnt Name="USD-MDY.P">
  <Undly ID="EUR-IFXGN.DE" PxStrctTyp="EQ_CORRELATION" IssuDtTm="2018-01-29" LastUpdateTm="2018-01-24"/>
  <Msr Val="0.612510110498455" ValTyp="Other" MktDataTyp="ASK"/>
</Pnt>


<Pnt Name="USD-ACT.N">
  <Undly ID="EUR-IFXGN.DE" PxStrctTyp="EQ_CORRELATION" IssuDtTm="2018-01-29" LastUpdateTm="2018-01-24"/>
  <Msr Val="0.416484093757645" ValTyp="Other" MktDataTyp="ASK"/>
</Pnt>


<Pnt Name="USD-XLV.N">
  <Undly ID="EUR-IFXGN.DE" PxStrctTyp="EQ_CORRELATION" IssuDtTm="2018-01-29" LastUpdateTm="2018-01-17"/>
  <Msr Val="0.554648812144518" ValTyp="Other" MktDataTyp="ASK"/>
</Pnt>


<Pnt Name="EUR-BAYG.DE">
  <Undly ID="EUR-IFXGN.DE" PxStrctTyp="EQ_CORRELATION" IssuDtTm="2018-01-29" LastUpdateTm="2018-01-24"/>
  <Msr Val="0.606357044578678" ValTyp="Other" MktDataTyp="ASK"/>
</Pnt>


<Pnt Name="EUR-BBV.MC">
  <Undly ID="EUR-IFXGN.DE" PxStrctTyp="EQ_CORRELATION" IssuDtTm="2018-01-29" LastUpdateTm="2018-01-24"/>
  <Msr Val="0.568464244293812" ValTyp="Other" MktDataTyp="ASK"/>
</Pnt>


<Pnt Name="USD-EWZ.N">
  <Undly ID="EUR-IFXGN.DE" PxStrctTyp="EQ_CORRELATION" IssuDtTm="2018-01-29" LastUpdateTm="2018-01-24"/>
  <Msr Val="0.439982042390229" ValTyp="Other" MktDataTyp="ASK"/>
</Pnt>


<Pnt Name="EUR-CONG.DE">
  <Undly ID="EUR-IFXGN.DE" PxStrctTyp="EQ_CORRELATION" IssuDtTm="2018-01-29" LastUpdateTm="2018-01-24"/>
  <Msr Val="0.673182894103687" ValTyp="Other" MktDataTyp="ASK"/>
</Pnt>


<Pnt Name="USD-BK.N">
  <Undly ID="EUR-IFXGN.DE" PxStrctTyp="EQ_CORRELATION" IssuDtTm="2018-01-29" LastUpdateTm="2018-01-24"/>
  <Msr Val="0.523627782971263" ValTyp="Other" MktDataTyp="ASK"/>
</Pnt>


<Pnt Name="GBP-DGE.L">
  <Undly ID="EUR-IFXGN.DE" PxStrctTyp="EQ_CORRELATION" IssuDtTm="2018-01-29" LastUpdateTm="2018-01-24"/>
  <Msr Val="0.469402158569606" ValTyp="Other" MktDataTyp="ASK"/>
</Pnt>


<Pnt Name="USD-LLY.N">
  <Undly ID="EUR-IFXGN.DE" PxStrctTyp="EQ_CORRELATION" IssuDtTm="2018-01-29" LastUpdateTm="2018-01-24"/>
  <Msr Val="0.453528884428383" ValTyp="Other" MktDataTyp="ASK"/>
</Pnt>


<Pnt Name="SEK-HMB.ST">
  <Undly ID="EUR-IFXGN.DE" PxStrctTyp="EQ_CORRELATION" IssuDtTm="2018-01-29" LastUpdateTm="2018-01-24"/>
  <Msr Val="0.533712102515602" ValTyp="Other" MktDataTyp="ASK"/>
</Pnt>


<Pnt Name="CHF-HOLN.S">
  <Undly ID="EUR-IFXGN.DE" PxStrctTyp="EQ_CORRELATION" IssuDtTm="2018-01-29" LastUpdateTm="2018-01-24"/>
  <Msr Val="0.607018641892255" ValTyp="Other" MktDataTyp="ASK"/>
</Pnt>


<Pnt Name="USD-VALE.N">
  <Undly ID="EUR-IFXGN.DE" PxStrctTyp="EQ_CORRELATION" IssuDtTm="2018-01-29" LastUpdateTm="2018-01-17"/>
  <Msr Val="0.419925541354554" ValTyp="Other" MktDataTyp="ASK"/>
</Pnt>


<Pnt Name="EUR-TEF.MC">
  <Undly ID="EUR-IFXGN.DE" PxStrctTyp="EQ_CORRELATION" IssuDtTm="2018-01-29" LastUpdateTm="2018-01-24"/>
  <Msr Val="0.560584974997414" ValTyp="Other" MktDataTyp="ASK"/>
</Pnt>


<Pnt Name="USD-KEY.N">
  <Undly ID="EUR-IFXGN.DE" PxStrctTyp="EQ_CORRELATION" IssuDtTm="2018-01-29" LastUpdateTm="2018-01-24"/>
  <Msr Val="0.499487715038831" ValTyp="Other" MktDataTyp="ASK"/>
</Pnt>


<Pnt Name="USD-UNH.N">
  <Undly ID="EUR-IFXGN.DE" PxStrctTyp="EQ_CORRELATION" IssuDtTm="2018-01-29" LastUpdateTm="2018-01-17"/>
  <Msr Val="0.471000153331799" ValTyp="Other" MktDataTyp="ASK"/>
</Pnt>


<Pnt Name="USD-MRK.N">
  <Undly ID="EUR-IFXGN.DE" PxStrctTyp="EQ_CORRELATION" IssuDtTm="2018-01-29" LastUpdateTm="2018-01-24"/>
  <Msr Val="0.457586547464817" ValTyp="Other" MktDataTyp="ASK"/>
</Pnt>


<Pnt Name="EUR-SASY.PA">
  <Undly ID="EUR-IFXGN.DE" PxStrctTyp="EQ_CORRELATION" IssuDtTm="2018-01-29" LastUpdateTm="2018-01-24"/>
  <Msr Val="0.537997578901915" ValTyp="Other" MktDataTyp="ASK"/>
</Pnt>


<Pnt Name="EUR-DBKGN.DE">
  <Undly ID="EUR-IFXGN.DE" PxStrctTyp="EQ_CORRELATION" IssuDtTm="2018-01-29" LastUpdateTm="2018-01-24"/>
  <Msr Val="0.582862712069859" ValTyp="Other" MktDataTyp="ASK"/>
</Pnt>


<Pnt Name="CHF-ZURN.S">
  <Undly ID="EUR-IFXGN.DE" PxStrctTyp="EQ_CORRELATION" IssuDtTm="2018-01-29" LastUpdateTm="2018-01-24"/>
  <Msr Val="0.56574144794704" ValTyp="Other" MktDataTyp="ASK"/>
</Pnt>


<Pnt Name="GBP-RDSB.L">
  <Undly ID="EUR-IFXGN.DE" PxStrctTyp="EQ_CORRELATION" IssuDtTm="2018-01-29" LastUpdateTm="2018-01-24"/>
  <Msr Val="0.432556567097864" ValTyp="Other" MktDataTyp="ASK"/>
</Pnt>


<Pnt Name="USD-GM.N">
  <Undly ID="EUR-IFXGN.DE" PxStrctTyp="EQ_CORRELATION" IssuDtTm="2018-01-29" LastUpdateTm="2018-01-24"/>
  <Msr Val="0.527978463075521" ValTyp="Other" MktDataTyp="ASK"/>
</Pnt>


<Pnt Name="USD-FCX.N">
  <Undly ID="EUR-IFXGN.DE" PxStrctTyp="EQ_CORRELATION" IssuDtTm="2018-01-29" LastUpdateTm="2018-01-24"/>
  <Msr Val="0.434094265333662" ValTyp="Other" MktDataTyp="ASK"/>
</Pnt>


<Pnt Name="SEK-SEBA.ST">
  <Undly ID="EUR-IFXGN.DE" PxStrctTyp="EQ_CORRELATION" IssuDtTm="2018-01-29" LastUpdateTm="2018-01-24"/>
  <Msr Val="0.609014443923728" ValTyp="Other" MktDataTyp="ASK"/>
</Pnt>


<Pnt Name="USD-GG.N">
  <Undly ID="EUR-IFXGN.DE" PxStrctTyp="EQ_CORRELATION" IssuDtTm="2018-01-29" LastUpdateTm="2018-01-24"/>
  <Msr Val="0.31974125877622" ValTyp="Other" MktDataTyp="ASK"/>
</Pnt>


<Pnt Name="USD-VZ.N">
  <Undly ID="EUR-IFXGN.DE" PxStrctTyp="EQ_CORRELATION" IssuDtTm="2018-01-29" LastUpdateTm="2018-01-17"/>
  <Msr Val="0.375322731166662" ValTyp="Other" MktDataTyp="ASK"/>
</Pnt>


<Pnt Name="EUR-PERP.PA">
  <Undly ID="EUR-IFXGN.DE" PxStrctTyp="EQ_CORRELATION" IssuDtTm="2018-01-29" LastUpdateTm="2018-01-24"/>
  <Msr Val="0.557825436087137" ValTyp="Other" MktDataTyp="ASK"/>
</Pnt>


<Pnt Name="USD-HWP.N">
  <Undly ID="EUR-IFXGN.DE" PxStrctTyp="EQ_CORRELATION" IssuDtTm="2018-01-29" LastUpdateTm="2018-01-24"/>
  <Msr Val="0.522045642531739" ValTyp="Other" MktDataTyp="ASK"/>
</Pnt>


<Pnt Name="USD-MDLZV.O">
  <Undly ID="EUR-IFXGN.DE" PxStrctTyp="EQ_CORRELATION" IssuDtTm="2018-01-29" LastUpdateTm="2018-01-24"/>
  <Msr Val="0.471907523357165" ValTyp="Other" MktDataTyp="ASK"/>
</Pnt>


<Pnt Name="USD-BRKB.N">
  <Undly ID="EUR-IFXGN.DE" PxStrctTyp="EQ_CORRELATION" IssuDtTm="2018-01-29" LastUpdateTm="2018-01-24"/>
  <Msr Val="0.528852334975179" ValTyp="Other" MktDataTyp="ASK"/>
</Pnt>


<Pnt Name="USD-GS.N">
  <Undly ID="EUR-IFXGN.DE" PxStrctTyp="EQ_CORRELATION" IssuDtTm="2018-01-29" LastUpdateTm="2018-01-24"/>
  <Msr Val="0.545470676993318" ValTyp="Other" MktDataTyp="ASK"/>
</Pnt>


<Pnt Name="EUR-HEIG.DE">
  <Undly ID="EUR-IFXGN.DE" PxStrctTyp="EQ_CORRELATION" IssuDtTm="2018-01-29" LastUpdateTm="2018-01-24"/>
  <Msr Val="0.643745228303411" ValTyp="Other" MktDataTyp="ASK"/>
</Pnt>


<Pnt Name="USD-INTC.O">
  <Undly ID="EUR-IFXGN.DE" PxStrctTyp="EQ_CORRELATION" IssuDtTm="2018-01-29" LastUpdateTm="2018-01-24"/>
  <Msr Val="0.587490219473708" ValTyp="Other" MktDataTyp="ASK"/>
</Pnt>


<Pnt Name="USD-ISRG.OQ">
  <Undly ID="EUR-IFXGN.DE" PxStrctTyp="EQ_CORRELATION" IssuDtTm="2018-01-29" LastUpdateTm="2018-01-24"/>
  <Msr Val="0.439165061860429" ValTyp="Other" MktDataTyp="ASK"/>
</Pnt>


<Pnt Name="USD-BA.N">
  <Undly ID="EUR-IFXGN.DE" PxStrctTyp="EQ_CORRELATION" IssuDtTm="2018-01-29" LastUpdateTm="2018-01-24"/>
  <Msr Val="0.534405205339028" ValTyp="Other" MktDataTyp="ASK"/>
</Pnt>


<Pnt Name="EUR-OREP.PA">
  <Undly ID="EUR-IFXGN.DE" PxStrctTyp="EQ_CORRELATION" IssuDtTm="2018-01-29" LastUpdateTm="2018-01-24"/>
  <Msr Val="0.579074948854373" ValTyp="Other" MktDataTyp="ASK"/>
</Pnt>


<Pnt Name="USD-F.N">
  <Undly ID="EUR-IFXGN.DE" PxStrctTyp="EQ_CORRELATION" IssuDtTm="2018-01-29" LastUpdateTm="2018-01-24"/>
  <Msr Val="0.498804393573059" ValTyp="Other" MktDataTyp="ASK"/>
</Pnt>


<Pnt Name="EUR-ALVG.DE">
  <Undly ID="EUR-IFXGN.DE" PxStrctTyp="EQ_CORRELATION" IssuDtTm="2018-01-29" LastUpdateTm="2018-01-24"/>
  <Msr Val="0.613023540739665" ValTyp="Other" MktDataTyp="ASK"/>
</Pnt>


<Pnt Name="USD-XME.N">
  <Undly ID="EUR-IFXGN.DE" PxStrctTyp="EQ_CORRELATION" IssuDtTm="2018-01-29" LastUpdateTm="2018-01-17"/>
  <Msr Val="0.462950961416778" ValTyp="Other" MktDataTyp="ASK"/>
</Pnt>


<Pnt Name="USD-CSCO.O">
  <Undly ID="EUR-IFXGN.DE" PxStrctTyp="EQ_CORRELATION" IssuDtTm="2018-01-29" LastUpdateTm="2018-01-24"/>
  <Msr Val="0.55128271737171" ValTyp="Other" MktDataTyp="ASK"/>
</Pnt>


<Pnt Name="GBP-BARC.L">
  <Undly ID="EUR-IFXGN.DE" PxStrctTyp="EQ_CORRELATION" IssuDtTm="2018-01-29" LastUpdateTm="2018-01-24"/>
  <Msr Val="0.534780755910483" ValTyp="Other" MktDataTyp="ASK"/>
</Pnt>


<Pnt Name="USD-APC.N">
  <Undly ID="EUR-IFXGN.DE" PxStrctTyp="EQ_CORRELATION" IssuDtTm="2018-01-29" LastUpdateTm="2018-01-24"/>
  <Msr Val="0.415820450557538" ValTyp="Other" MktDataTyp="ASK"/>
</Pnt>


<Pnt Name="EUR-HNKG_P.DE">
  <Undly ID="EUR-IFXGN.DE" PxStrctTyp="EQ_CORRELATION" IssuDtTm="2018-01-29" LastUpdateTm="2018-01-24"/>
  <Msr Val="0.572434973003451" ValTyp="Other" MktDataTyp="ASK"/>
</Pnt>


<Pnt Name="USD-FL.N">
  <Undly ID="EUR-IFXGN.DE" PxStrctTyp="EQ_CORRELATION" IssuDtTm="2018-01-29" LastUpdateTm="2018-01-24"/>
  <Msr Val="0.448126909164526" ValTyp="Other" MktDataTyp="ASK"/>
</Pnt>


<Pnt Name="USD-ESRX.O">
  <Undly ID="EUR-IFXGN.DE" PxStrctTyp="EQ_CORRELATION" IssuDtTm="2018-01-29" LastUpdateTm="2018-01-24"/>
  <Msr Val="0.467683387405785" ValTyp="Other" MktDataTyp="ASK"/>
</Pnt>


<Pnt Name="USD-DD.N">
  <Undly ID="EUR-IFXGN.DE" PxStrctTyp="EQ_CORRELATION" IssuDtTm="2018-01-29" LastUpdateTm="2018-01-24"/>
  <Msr Val="0.478186812359711" ValTyp="Other" MktDataTyp="ASK"/>
</Pnt>


<Pnt Name="USD-COST.O">
  <Undly ID="EUR-IFXGN.DE" PxStrctTyp="EQ_CORRELATION" IssuDtTm="2018-01-29" LastUpdateTm="2018-01-24"/>
  <Msr Val="0.461362318635427" ValTyp="Other" MktDataTyp="ASK"/>
</Pnt>


<Pnt Name="USD-CCL.N">
  <Undly ID="EUR-IFXGN.DE" PxStrctTyp="EQ_CORRELATION" IssuDtTm="2018-01-29" LastUpdateTm="2018-01-24"/>
  <Msr Val="0.507315380034058" ValTyp="Other" MktDataTyp="ASK"/>
</Pnt>


<Pnt Name="USD-RTY INDEX">
  <Undly ID="EUR-IFXGN.DE" PxStrctTyp="EQ_CORRELATION" IssuDtTm="2018-01-29" LastUpdateTm="2018-01-24"/>
  <Msr Val="0.591540364392715" ValTyp="Other" MktDataTyp="ASK"/>
</Pnt>


<Pnt Name="USD-AAPL.O">
  <Undly ID="EUR-IFXGN.DE" PxStrctTyp="EQ_CORRELATION" IssuDtTm="2018-01-29" LastUpdateTm="2018-01-24"/>
  <Msr Val="0.537890751302794" ValTyp="Other" MktDataTyp="ASK"/>
</Pnt>


<Pnt Name="EUR-AEGN.AS">
  <Undly ID="EUR-IFXGN.DE" PxStrctTyp="EQ_CORRELATION" IssuDtTm="2018-01-29" LastUpdateTm="2018-01-24"/>
  <Msr Val="0.589671348358425" ValTyp="Other" MktDataTyp="ASK"/>
</Pnt>


<Pnt Name="USD-VWO.N">
  <Undly ID="EUR-IFXGN.DE" PxStrctTyp="EQ_CORRELATION" IssuDtTm="2018-01-29" LastUpdateTm="2018-01-17"/>
  <Msr Val="0.565663960591275" ValTyp="Other" MktDataTyp="ASK"/>
</Pnt>


<Pnt Name="EUR-SGOB.PA">
  <Undly ID="EUR-IFXGN.DE" PxStrctTyp="EQ_CORRELATION" IssuDtTm="2018-01-29" LastUpdateTm="2018-01-24"/>
  <Msr Val="0.633065745074616" ValTyp="Other" MktDataTyp="ASK"/>
</Pnt>


<Pnt Name="USD-TMUS.N">
  <Undly ID="EUR-IFXGN.DE" PxStrctTyp="EQ_CORRELATION" IssuDtTm="2018-01-29" LastUpdateTm="2018-01-17"/>
  <Msr Val="0.411906760727025" ValTyp="Other" MktDataTyp="ASK"/>
</Pnt>


<Pnt Name="USD-COP.N">
  <Undly ID="EUR-IFXGN.DE" PxStrctTyp="EQ_CORRELATION" IssuDtTm="2018-01-29" LastUpdateTm="2018-01-24"/>
  <Msr Val="0.431041268573978" ValTyp="Other" MktDataTyp="ASK"/>
</Pnt>


<Pnt Name="USD-STX.O">
  <Undly ID="EUR-IFXGN.DE" PxStrctTyp="EQ_CORRELATION" IssuDtTm="2018-01-29" LastUpdateTm="2018-01-17"/>
  <Msr Val="0.520797076985184" ValTyp="Other" MktDataTyp="ASK"/>
</Pnt>


<Pnt Name="GBP-RIO.L">
  <Undly ID="EUR-IFXGN.DE" PxStrctTyp="EQ_CORRELATION" IssuDtTm="2018-01-29" LastUpdateTm="2018-01-24"/>
  <Msr Val="0.435014571444776" ValTyp="Other" MktDataTyp="ASK"/>
</Pnt>


<Pnt Name="SEK-SWEDA.ST">
  <Undly ID="EUR-IFXGN.DE" PxStrctTyp="EQ_CORRELATION" IssuDtTm="2018-01-29" LastUpdateTm="2018-01-24"/>
  <Msr Val="0.627511288794906" ValTyp="Other" MktDataTyp="ASK"/>
</Pnt>


<Pnt Name="EUR-EAD.PA">
  <Undly ID="EUR-IFXGN.DE" PxStrctTyp="EQ_CORRELATION" IssuDtTm="2018-01-29" LastUpdateTm="2018-01-24"/>
  <Msr Val="0.549221310998451" ValTyp="Other" MktDataTyp="ASK"/>
</Pnt>


<Pnt Name="EUR-INTB.BR">
  <Undly ID="EUR-IFXGN.DE" PxStrctTyp="EQ_CORRELATION" IssuDtTm="2018-01-29" LastUpdateTm="2018-01-24"/>
  <Msr Val="0.56910234295755" ValTyp="Other" MktDataTyp="ASK"/>
</Pnt>


<Pnt Name="USD-MU.O">
  <Undly ID="EUR-IFXGN.DE" PxStrctTyp="EQ_CORRELATION" IssuDtTm="2018-01-29" LastUpdateTm="2018-01-24"/>
  <Msr Val="0.571711959983872" ValTyp="Other" MktDataTyp="ASK"/>
</Pnt>



<Pnt Name="EUR-AUD">
  <Undly ID="EUR-IFXGN.DE" PxStrctTyp="EQ_CORRELATION" IssuDtTm="2018-01-29" LastUpdateTm="2018-01-17"/>
  <Msr Val="-0.314106678946035" ValTyp="Other" MktDataTyp="ASK"/>
</Pnt>


<Pnt Name="EUR-GBP">
  <Undly ID="EUR-IFXGN.DE" PxStrctTyp="EQ_CORRELATION" IssuDtTm="2018-01-29" LastUpdateTm="2018-01-17"/>
  <Msr Val="-0.271612938714041" ValTyp="Other" MktDataTyp="ASK"/>
</Pnt>


<Pnt Name="EUR-CAD">
  <Undly ID="EUR-IFXGN.DE" PxStrctTyp="EQ_CORRELATION" IssuDtTm="2018-01-29" LastUpdateTm="2018-01-17"/>
  <Msr Val="-0.292136831054121" ValTyp="Other" MktDataTyp="ASK"/>
</Pnt>


<Pnt Name="EUR-MXN">
  <Undly ID="EUR-IFXGN.DE" PxStrctTyp="EQ_CORRELATION" IssuDtTm="2018-01-29" LastUpdateTm="2018-01-17"/>
  <Msr Val="-0.400800303009382" ValTyp="Other" MktDataTyp="ASK"/>
</Pnt>


<Pnt Name="EUR-USD">
  <Undly ID="EUR-IFXGN.DE" PxStrctTyp="EQ_CORRELATION" IssuDtTm="2018-01-29" LastUpdateTm="2018-01-16"/>
  <Msr Val="-0.44769030228413" ValTyp="Other" MktDataTyp="ASK"/>
</Pnt>


<Pnt Name="EUR-SEK">
  <Undly ID="EUR-IFXGN.DE" PxStrctTyp="EQ_CORRELATION" IssuDtTm="2018-01-29" LastUpdateTm="2018-01-17"/>
  <Msr Val="-0.419471068777234" ValTyp="Other" MktDataTyp="ASK"/>
</Pnt>


<Pnt Name="EUR-KRW">
  <Undly ID="EUR-IFXGN.DE" PxStrctTyp="EQ_CORRELATION" IssuDtTm="2018-01-29" LastUpdateTm="2018-01-17"/>
  <Msr Val="-0.436290432351536" ValTyp="Other" MktDataTyp="ASK"/>
</Pnt>


<Pnt Name="EUR-JPY">
  <Undly ID="EUR-IFXGN.DE" PxStrctTyp="EQ_CORRELATION" IssuDtTm="2018-01-29" LastUpdateTm="2018-01-17"/>
  <Msr Val="0.00348123133700182" ValTyp="Other" MktDataTyp="ASK"/>
</Pnt>


<Pnt Name="EUR-CHF">
  <Undly ID="EUR-IFXGN.DE" PxStrctTyp="EQ_CORRELATION" IssuDtTm="2018-01-29" LastUpdateTm="2018-01-17"/>
  <Msr Val="-0.126145753288664" ValTyp="Other" MktDataTyp="ASK"/>
</Pnt>


<Pnt Name="EUR-HKD">
  <Undly ID="EUR-IFXGN.DE" PxStrctTyp="EQ_CORRELATION" IssuDtTm="2018-01-29" LastUpdateTm="2018-01-17"/>
  <Msr Val="-0.275667571385662" ValTyp="Other" MktDataTyp="ASK"/>
</Pnt>



</Mkt>
